{
  "created": "2025-12-18T06:16:21+01:00",
  "update": "2025-12-18T07:16:21+01:00",
  "uv": {
    "duration": {
      "days": 2,
      "hours": 11
    },
    "url": "https://dsa.no/sol-og-solarium/slik-beskytter-du-deg-i-sola",
    "displayUrl": "dsa.no"
  },
  "dayIntervals": [
    {
      "start": "2025-12-18T07:00:00+01:00",
      "end": "2025-12-18T23:00:00+01:00",
      "twentyFourHourSymbol": "fog",
      "twelveHourSymbols": [
        "fog",
        "clearsky_day"
      ],
      "sixHourSymbols": [
        null,
        "fog",
        "fair_day",
        "clearsky_night"
      ],
      "symbolConfidence": "None",
      "precipitation": {
        "value": 0
      },
      "temperature": {
        "value": 7.6,
        "min": 1.6,
        "max": 7.6
      },
      "wind": {
        "min": 0.4,
        "max": 1.8
      }
    },
    {
      "start": "2025-12-19T00:00:00+01:00",
      "end": "2025-12-19T23:00:00+01:00",
      "twentyFourHourSymbol": "lightrainshowers_day",
      "twelveHourSymbols": [
        "clearsky_day",
        "lightrainshowers_day"
      ],
      "sixHourSymbols": [
        "clearsky_night",
        "fair_day",
        "rainshowers_day",
        "lightrain"
      ],
      "symbolConfidence": "None",
      "precipitation": {
        "value": 3.5
      },
      "temperature": {
        "value": 8.5,
        "min": 2,
        "max": 8.5
      },
      "wind": {
        "min": 0.6,
        "max": 1.6
      }
    },
    {
      "start": "2025-12-20T00:00:00+01:00",
      "end": "2025-12-20T23:00:00+01:00",
      "twentyFourHourSymbol": "cloudy",
      "twelveHourSymbols": [
        "lightrain",
        "lightrain"
      ],
      "sixHourSymbols": [
        "rain",
        "partlycloudy_day",
        "cloudy",
        "rain"
      ],
      "symbolConfidence": "None",
      "precipitation": {
        "value": 3.6
      },
      "temperature": {
        "value": 7.1,
        "min": 4.7,
        "max": 7.9
      },
      "wind": {
        "min": 1.1,
        "max": 1.4
      }
    },
    {
      "start": "2025-12-21T00:00:00+01:00",
      "end": "2025-12-21T23:00:00+01:00",
      "twentyFourHourSymbol": "lightrain",
      "twelveHourSymbols": [
        "cloudy",
        "lightrain"
      ],
      "sixHourSymbols": [
        "cloudy",
        "cloudy",
        "rain",
        "cloudy"
      ],
      "symbolConfidence": "None",
      "precipitation": {
        "value": 2.7
      },
      "temperature": {
        "value": 6.4,
        "min": 4.2,
        "max": 6.9
      },
      "wind": {
        "min": 0.1,
        "max": 0.4
      }
    },
    {
      "start": "2025-12-22T00:00:00+01:00",
      "end": "2025-12-22T23:00:00+01:00",
      "twentyFourHourSymbol": "cloudy",
      "twelveHourSymbols": [
        "cloudy",
        "cloudy"
      ],
      "sixHourSymbols": [
        "cloudy",
        "cloudy",
        "cloudy",
        "cloudy"
      ],
      "symbolConfidence": "None",
      "precipitation": {
        "value": 0
      },
      "temperature": {
        "value": 7.6,
        "min": 1.1,
        "max": 7.8
      },
      "wind": {
        "min": 0.5,
        "max": 1.4
      }
    },
    {
      "start": "2025-12-23T00:00:00+01:00",
      "end": "2025-12-23T23:00:00+01:00",
      "twentyFourHourSymbol": "cloudy",
      "twelveHourSymbols": [
        "cloudy",
        "cloudy"
      ],
      "sixHourSymbols": [
        "cloudy",
        "partlycloudy_day",
        "cloudy",
        "cloudy"
      ],
      "symbolConfidence": "None",
      "precipitation": {
        "value": 0
      },
      "temperature": {
        "value": 5.8,
        "min": 1.1,
        "max": 6.7
      },
      "wind": {
        "min": 0.3,
        "max": 1
      }
    },
    {
      "start": "2025-12-24T00:00:00+01:00",
      "end": "2025-12-24T23:00:00+01:00",
      "twentyFourHourSymbol": "cloudy",
      "twelveHourSymbols": [
        "cloudy",
        "cloudy"
      ],
      "sixHourSymbols": [
        "cloudy",
        "cloudy",
        "cloudy",
        "cloudy"
      ],
      "symbolConfidence": "None",
      "precipitation": {
        "value": 0
      },
      "temperature": {
        "value": 4.8,
        "min": 1.1,
        "max": 5.3
      },
      "wind": {
        "min": 1.1,
        "max": 3.4
      }
    },
    {
      "start": "2025-12-25T00:00:00+01:00",
      "end": "2025-12-25T23:00:00+01:00",
      "twentyFourHourSymbol": "partlycloudy_day",
      "twelveHourSymbols": [
        "cloudy",
        "partlycloudy_day"
      ],
      "sixHourSymbols": [
        "cloudy",
        "cloudy",
        "cloudy",
        "fair_night"
      ],
      "symbolConfidence": "None",
      "precipitation": {
        "value": 0
      },
      "temperature": {
        "value": 0.9,
        "min": -1.5,
        "max": 2
      },
      "wind": {
        "min": 3.3,
        "max": 4.9
      }
    },
    {
      "start": "2025-12-26T00:00:00+01:00",
      "end": "2025-12-26T23:00:00+01:00",
      "twentyFourHourSymbol": "lightsnow",
      "twelveHourSymbols": [
        "cloudy",
        "lightsnowshowers_day"
      ],
      "sixHourSymbols": [
        "partlycloudy_night",
        "cloudy",
        "lightsnow",
        "cloudy"
      ],
      "symbolConfidence": "None",
      "precipitation": {
        "value": 1.1
      },
      "temperature": {
        "value": -1,
        "min": -2.2,
        "max": -0.2
      },
      "wind": {
        "min": 1.4,
        "max": 4.6
      }
    }
  ],
  "shortIntervals": [
    {
      "symbol": {
        "n": 15,
        "clouds": 3,
        "precip": 0,
        "sunup": false
      },
      "symbolCode": {
        "next1Hour": "fog",
        "next6Hours": "fog",
        "next12Hours": "fair_day"
      },
      "precipitation": {
        "value": 0
      },
      "temperature": {
        "value": 1.6
      },
      "wind": {
        "direction": 223,
        "speed": 1.4
      },
      "feelsLike": {
        "value": 0
      },
      "pressure": {
        "value": 1026
      },
      "uvIndex": {
        "value": 0
      },
      "cloudCover": {
        "value": 99,
        "high": 97,
        "middle": 0,
        "low": 63,
        "fog": 40
      },
      "humidity": {
        "value": 93.9
      },
      "dewPoint": {
        "value": 0.6
      },
      "start": "2025-12-18T08:00:00+01:00",
      "end": "2025-12-18T09:00:00+01:00"
    },
    {
      "symbol": {
        "n": 15,
        "clouds": 3,
        "precip": 0,
        "sunup": false
      },
      "symbolCode": {
        "next1Hour": "fog",
        "next6Hours": "partlycloudy_day",
        "next12Hours": "fair_day"
      },
      "precipitation": {
        "value": 0
      },
      "temperature": {
        "value": 2.3
      },
      "wind": {
        "direction": 244,
        "speed": 1.4
      },
      "feelsLike": {
        "value": 1
      },
      "pressure": {
        "value": 1027
      },
      "uvIndex": {
        "value": 0.1
      },
      "cloudCover": {
        "value": 99,
        "high": 97,
        "middle": 0,
        "low": 64,
        "fog": 43
      },
      "humidity": {
        "value": 94
      },
      "dewPoint": {
        "value": 1.3
      },
      "start": "2025-12-18T09:00:00+01:00",
      "end": "2025-12-18T10:00:00+01:00"
    },
    {
      "symbol": {
        "n": 15,
        "clouds": 3,
        "precip": 0,
        "sunup": false
      },
      "symbolCode": {
        "next1Hour": "fog",
        "next6Hours": "fair_day",
        "next12Hours": "fair_day"
      },
      "precipitation": {
        "value": 0
      },
      "temperature": {
        "value": 3.6
      },
      "wind": {
        "direction": 254,
        "speed": 1.6
      },
      "feelsLike": {
        "value": 2
      },
      "pressure": {
        "value": 1027
      },
      "uvIndex": {
        "value": 0.4
      },
      "cloudCover": {
        "value": 98,
        "high": 96,
        "middle": 0,
        "low": 61,
        "fog": 40
      },
      "humidity": {
        "value": 92.3
      },
      "dewPoint": {
        "value": 2.3
      },
      "start": "2025-12-18T10:00:00+01:00",
      "end": "2025-12-18T11:00:00+01:00"
    },
    {
      "symbol": {
        "n": 15,
        "clouds": 3,
        "precip": 0,
        "sunup": false
      },
      "symbolCode": {
        "next1Hour": "fog",
        "next6Hours": "fair_day",
        "next12Hours": "clearsky_day"
      },
      "precipitation": {
        "value": 0
      },
      "temperature": {
        "value": 4.7
      },
      "wind": {
        "direction": 267,
        "speed": 1.6
      },
      "feelsLike": {
        "value": 3
      },
      "pressure": {
        "value": 1026
      },
      "uvIndex": {
        "value": 0.7
      },
      "cloudCover": {
        "value": 85,
        "high": 60,
        "middle": 0,
        "low": 70,
        "fog": 38
      },
      "humidity": {
        "value": 92
      },
      "dewPoint": {
        "value": 3.4
      },
      "start": "2025-12-18T11:00:00+01:00",
      "end": "2025-12-18T12:00:00+01:00"
    },
    {
      "symbol": {
        "n": 15,
        "clouds": 3,
        "precip": 0,
        "sunup": false
      },
      "symbolCode": {
        "next1Hour": "fog",
        "next6Hours": "fair_day",
        "next12Hours": "clearsky_day"
      },
      "precipitation": {
        "value": 0
      },
      "temperature": {
        "value": 6
      },
      "wind": {
        "direction": 261,
        "speed": 1.8
      },
      "feelsLike": {
        "value": 5
      },
      "pressure": {
        "value": 1026
      },
      "uvIndex": {
        "value": 0.9
      },
      "cloudCover": {
        "value": 55,
        "high": 3,
        "middle": 0,
        "low": 54,
        "fog": 28
      },
      "humidity": {
        "value": 93.6
      },
      "dewPoint": {
        "value": 5
      },
      "start": "2025-12-18T12:00:00+01:00",
      "end": "2025-12-18T13:00:00+01:00"
    },
    {
      "symbol": {
        "n": 3,
        "clouds": 2,
        "precip": 0,
        "var": "Sun",
        "sunup": false
      },
      "symbolCode": {
        "next1Hour": "partlycloudy_day",
        "next6Hours": "clearsky_day",
        "next12Hours": "clearsky_day"
      },
      "precipitation": {
        "value": 0
      },
      "temperature": {
        "value": 7
      },
      "wind": {
        "direction": 238,
        "speed": 1.4
      },
      "feelsLike": {
        "value": 6
      },
      "pressure": {
        "value": 1025
      },
      "uvIndex": {
        "value": 0.8
      },
      "cloudCover": {
        "value": 38,
        "high": 0,
        "middle": 0,
        "low": 38,
        "fog": 1
      },
      "humidity": {
        "value": 89.4
      },
      "dewPoint": {
        "value": 5.3
      },
      "start": "2025-12-18T13:00:00+01:00",
      "end": "2025-12-18T14:00:00+01:00"
    },
    {
      "symbol": {
        "n": 2,
        "clouds": 1,
        "precip": 0,
        "var": "Sun",
        "sunup": false
      },
      "symbolCode": {
        "next1Hour": "fair_day",
        "next6Hours": "clearsky_day",
        "next12Hours": "clearsky_day"
      },
      "precipitation": {
        "value": 0
      },
      "temperature": {
        "value": 7.6
      },
      "wind": {
        "direction": 228,
        "speed": 1.5
      },
      "feelsLike": {
        "value": 7
      },
      "pressure": {
        "value": 1024
      },
      "uvIndex": {
        "value": 0.6
      },
      "cloudCover": {
        "value": 21,
        "high": 0,
        "middle": 0,
        "low": 20,
        "fog": 0
      },
      "humidity": {
        "value": 84.2
      },
      "dewPoint": {
        "value": 5
      },
      "start": "2025-12-18T14:00:00+01:00",
      "end": "2025-12-18T15:00:00+01:00"
    },
    {
      "symbol": {
        "n": 1,
        "clouds": 0,
        "precip": 0,
        "var": "Sun",
        "sunup": false
      },
      "symbolCode": {
        "next1Hour": "clearsky_day",
        "next6Hours": "clearsky_day",
        "next12Hours": "clearsky_day"
      },
      "precipitation": {
        "value": 0
      },
      "temperature": {
        "value": 7.4
      },
      "wind": {
        "direction": 242,
        "speed": 1.2
      },
      "feelsLike": {
        "value": 7.4
      },
      "pressure": {
        "value": 1023
      },
      "uvIndex": {
        "value": 0.3
      },
      "cloudCover": {
        "value": 12,
        "high": 0,
        "middle": 0,
        "low": 12,
        "fog": 0
      },
      "humidity": {
        "value": 84.7
      },
      "dewPoint": {
        "value": 4.9
      },
      "start": "2025-12-18T15:00:00+01:00",
      "end": "2025-12-18T16:00:00+01:00"
    },
    {
      "symbol": {
        "n": 1,
        "clouds": 0,
        "precip": 0,
        "var": "Sun",
        "sunup": false
      },
      "symbolCode": {
        "next1Hour": "clearsky_day",
        "next6Hours": "clearsky_night",
        "next12Hours": "clearsky_night"
      },
      "precipitation": {
        "value": 0
      },
      "temperature": {
        "value": 5.4
      },
      "wind": {
        "direction": 297,
        "speed": 0.6
      },
      "feelsLike": {
        "value": 5.4
      },
      "pressure": {
        "value": 1023
      },
      "uvIndex": {
        "value": 0.1
      },
      "cloudCover": {
        "value": 5,
        "high": 0,
        "middle": 0,
        "low": 5,
        "fog": 0
      },
      "humidity": {
        "value": 91.6
      },
      "dewPoint": {
        "value": 4
      },
      "start": "2025-12-18T16:00:00+01:00",
      "end": "2025-12-18T17:00:00+01:00"
    },
    {
      "symbol": {
        "n": 1,
        "clouds": 0,
        "precip": 0,
        "var": "Moon",
        "sunup": false
      },
      "symbolCode": {
        "next1Hour": "clearsky_night",
        "next6Hours": "clearsky_night",
        "next12Hours": "clearsky_night"
      },
      "precipitation": {
        "value": 0
      },
      "temperature": {
        "value": 3.8
      },
      "wind": {
        "direction": 276,
        "speed": 0.6
      },
      "feelsLike": {
        "value": 3.8
      },
      "pressure": {
        "value": 1023
      },
      "uvIndex": {
        "value": 0
      },
      "cloudCover": {
        "value": 3,
        "high": 0,
        "middle": 0,
        "low": 3,
        "fog": 0
      },
      "humidity": {
        "value": 92
      },
      "dewPoint": {
        "value": 2.5
      },
      "start": "2025-12-18T17:00:00+01:00",
      "end": "2025-12-18T18:00:00+01:00"
    },
    {
      "symbol": {
        "n": 1,
        "clouds": 0,
        "precip": 0,
        "var": "Moon",
        "sunup": false
      },
      "symbolCode": {
        "next1Hour": "clearsky_night",
        "next6Hours": "clearsky_night",
        "next12Hours": "clearsky_night"
      },
      "precipitation": {
        "value": 0
      },
      "temperature": {
        "value": 3.4
      },
      "wind": {
        "direction": 250,
        "speed": 0.8
      },
      "feelsLike": {
        "value": 3.4
      },
      "pressure": {
        "value": 1022
      },
      "uvIndex": {
        "value": 0
      },
      "cloudCover": {
        "value": 2,
        "high": 0,
        "middle": 0,
        "low": 2,
        "fog": 0
      },
      "humidity": {
        "value": 89.5
      },
      "dewPoint": {
        "value": 1.7
      },
      "start": "2025-12-18T18:00:00+01:00",
      "end": "2025-12-18T19:00:00+01:00"
    },
    {
      "symbol": {
        "n": 1,
        "clouds": 0,
        "precip": 0,
        "var": "Moon",
        "sunup": false
      },
      "symbolCode": {
        "next1Hour": "clearsky_night",
        "next6Hours": "clearsky_night",
        "next12Hours": "clearsky_night"
      },
      "precipitation": {
        "value": 0
      },
      "temperature": {
        "value": 3.5
      },
      "wind": {
        "direction": 250,
        "speed": 0.7
      },
      "feelsLike": {
        "value": 3.5
      },
      "pressure": {
        "value": 1023
      },
      "uvIndex": {
        "value": 0
      },
      "cloudCover": {
        "value": 1,
        "high": 0,
        "middle": 1,
        "low": 1,
        "fog": 0
      },
      "humidity": {
        "value": 86.2
      },
      "dewPoint": {
        "value": 1.3
      },
      "start": "2025-12-18T19:00:00+01:00",
      "end": "2025-12-18T20:00:00+01:00"
    },
    {
      "symbol": {
        "n": 1,
        "clouds": 0,
        "precip": 0,
        "var": "Moon",
        "sunup": false
      },
      "symbolCode": {
        "next1Hour": "clearsky_night",
        "next6Hours": "clearsky_night",
        "next12Hours": "clearsky_night"
      },
      "precipitation": {
        "value": 0
      },
      "temperature": {
        "value": 3.3
      },
      "wind": {
        "direction": 268,
        "speed": 0.4
      },
      "feelsLike": {
        "value": 3.3
      },
      "pressure": {
        "value": 1023
      },
      "uvIndex": {
        "value": 0
      },
      "cloudCover": {
        "value": 1,
        "high": 0,
        "middle": 1,
        "low": 0,
        "fog": 0
      },
      "humidity": {
        "value": 84.6
      },
      "dewPoint": {
        "value": 0.8
      },
      "start": "2025-12-18T20:00:00+01:00",
      "end": "2025-12-18T21:00:00+01:00"
    },
    {
      "symbol": {
        "n": 1,
        "clouds": 0,
        "precip": 0,
        "var": "Moon",
        "sunup": false
      },
      "symbolCode": {
        "next1Hour": "clearsky_night",
        "next6Hours": "clearsky_night",
        "next12Hours": "clearsky_night"
      },
      "precipitation": {
        "value": 0
      },
      "temperature": {
        "value": 3.1
      },
      "wind": {
        "direction": 251,
        "speed": 0.6
      },
      "feelsLike": {
        "value": 3.1
      },
      "pressure": {
        "value": 1023
      },
      "uvIndex": {
        "value": 0
      },
      "cloudCover": {
        "value": 1,
        "high": 0,
        "middle": 0,
        "low": 0,
        "fog": 0
      },
      "humidity": {
        "value": 84.1
      },
      "dewPoint": {
        "value": 0.5
      },
      "start": "2025-12-18T21:00:00+01:00",
      "end": "2025-12-18T22:00:00+01:00"
    },
    {
      "symbol": {
        "n": 1,
        "clouds": 0,
        "precip": 0,
        "var": "Moon",
        "sunup": false
      },
      "symbolCode": {
        "next1Hour": "clearsky_night",
        "next6Hours": "clearsky_night",
        "next12Hours": "clearsky_night"
      },
      "precipitation": {
        "value": 0
      },
      "temperature": {
        "value": 2.9
      },
      "wind": {
        "direction": 235,
        "speed": 0.6
      },
      "feelsLike": {
        "value": 2.9
      },
      "pressure": {
        "value": 1023
      },
      "uvIndex": {
        "value": 0
      },
      "cloudCover": {
        "value": 6,
        "high": 1,
        "middle": 0,
        "low": 5,
        "fog": 5
      },
      "humidity": {
        "value": 83.9
      },
      "dewPoint": {
        "value": 0.3
      },
      "start": "2025-12-18T22:00:00+01:00",
      "end": "2025-12-18T23:00:00+01:00"
    },
    {
      "symbol": {
        "n": 1,
        "clouds": 0,
        "precip": 0,
        "var": "Moon",
        "sunup": false
      },
      "symbolCode": {
        "next1Hour": "clearsky_night",
        "next6Hours": "clearsky_night",
        "next12Hours": "clearsky_day"
      },
      "precipitation": {
        "value": 0
      },
      "temperature": {
        "value": 2.7
      },
      "wind": {
        "direction": 251,
        "speed": 0.6
      },
      "feelsLike": {
        "value": 2.7
      },
      "pressure": {
        "value": 1023
      },
      "uvIndex": {
        "value": 0
      },
      "cloudCover": {
        "value": 1,
        "high": 0,
        "middle": 0,
        "low": 0,
        "fog": 0
      },
      "humidity": {
        "value": 83.9
      },
      "dewPoint": {
        "value": 0.1
      },
      "start": "2025-12-18T23:00:00+01:00",
      "end": "2025-12-19T00:00:00+01:00"
    },
    {
      "symbol": {
        "n": 1,
        "clouds": 0,
        "precip": 0,
        "var": "Moon",
        "sunup": false
      },
      "symbolCode": {
        "next1Hour": "clearsky_night",
        "next6Hours": "clearsky_night",
        "next12Hours": "clearsky_day"
      },
      "precipitation": {
        "value": 0
      },
      "temperature": {
        "value": 2.5
      },
      "wind": {
        "direction": 249,
        "speed": 0.6
      },
      "feelsLike": {
        "value": 2.5
      },
      "pressure": {
        "value": 1023
      },
      "uvIndex": {
        "value": 0
      },
      "cloudCover": {
        "value": 1,
        "high": 0,
        "middle": 0,
        "low": 0,
        "fog": 0
      },
      "humidity": {
        "value": 85.1
      },
      "dewPoint": {
        "value": 0.1
      },
      "start": "2025-12-19T00:00:00+01:00",
      "end": "2025-12-19T01:00:00+01:00"
    },
    {
      "symbol": {
        "n": 1,
        "clouds": 0,
        "precip": 0,
        "var": "Moon",
        "sunup": false
      },
      "symbolCode": {
        "next1Hour": "clearsky_night",
        "next6Hours": "clearsky_night",
        "next12Hours": "clearsky_day"
      },
      "precipitation": {
        "value": 0
      },
      "temperature": {
        "value": 2.3
      },
      "wind": {
        "direction": 246,
        "speed": 0.7
      },
      "feelsLike": {
        "value": 2.3
      },
      "pressure": {
        "value": 1024
      },
      "uvIndex": {
        "value": 0
      },
      "cloudCover": {
        "value": 1,
        "high": 0,
        "middle": 0,
        "low": 1,
        "fog": 0
      },
      "humidity": {
        "value": 85.1
      },
      "dewPoint": {
        "value": -0.1
      },
      "start": "2025-12-19T01:00:00+01:00",
      "end": "2025-12-19T02:00:00+01:00"
    },
    {
      "symbol": {
        "n": 1,
        "clouds": 0,
        "precip": 0,
        "var": "Moon",
        "sunup": false
      },
      "symbolCode": {
        "next1Hour": "clearsky_night",
        "next6Hours": "clearsky_night",
        "next12Hours": "fair_day"
      },
      "precipitation": {
        "value": 0
      },
      "temperature": {
        "value": 2.2
      },
      "wind": {
        "direction": 261,
        "speed": 0.8
      },
      "feelsLike": {
        "value": 2.2
      },
      "pressure": {
        "value": 1024
      },
      "uvIndex": {
        "value": 0
      },
      "cloudCover": {
        "value": 2,
        "high": 0,
        "middle": 2,
        "low": 0,
        "fog": 0
      },
      "humidity": {
        "value": 85.2
      },
      "dewPoint": {
        "value": -0.2
      },
      "start": "2025-12-19T02:00:00+01:00",
      "end": "2025-12-19T03:00:00+01:00"
    },
    {
      "symbol": {
        "n": 1,
        "clouds": 0,
        "precip": 0,
        "var": "Moon",
        "sunup": false
      },
      "symbolCode": {
        "next1Hour": "clearsky_night",
        "next6Hours": "clearsky_night",
        "next12Hours": "fair_day"
      },
      "precipitation": {
        "value": 0
      },
      "temperature": {
        "value": 2.2
      },
      "wind": {
        "direction": 261,
        "speed": 0.8
      },
      "feelsLike": {
        "value": 2.2
      },
      "pressure": {
        "value": 1024
      },
      "uvIndex": {
        "value": 0
      },
      "cloudCover": {
        "value": 1,
        "high": 0,
        "middle": 1,
        "low": 0,
        "fog": 0
      },
      "humidity": {
        "value": 84.9
      },
      "dewPoint": {
        "value": -0.3
      },
      "start": "2025-12-19T03:00:00+01:00",
      "end": "2025-12-19T04:00:00+01:00"
    },
    {
      "symbol": {
        "n": 1,
        "clouds": 0,
        "precip": 0,
        "var": "Moon",
        "sunup": false
      },
      "symbolCode": {
        "next1Hour": "clearsky_night",
        "next6Hours": "clearsky_night",
        "next12Hours": "fair_day"
      },
      "precipitation": {
        "value": 0
      },
      "temperature": {
        "value": 2.2
      },
      "wind": {
        "direction": 262,
        "speed": 0.8
      },
      "feelsLike": {
        "value": 2.2
      },
      "pressure": {
        "value": 1023
      },
      "uvIndex": {
        "value": 0
      },
      "cloudCover": {
        "value": 1,
        "high": 0,
        "middle": 1,
        "low": 0,
        "fog": 0
      },
      "humidity": {
        "value": 84.5
      },
      "dewPoint": {
        "value": -0.3
      },
      "start": "2025-12-19T04:00:00+01:00",
      "end": "2025-12-19T05:00:00+01:00"
    },
    {
      "symbol": {
        "n": 1,
        "clouds": 0,
        "precip": 0,
        "var": "Moon",
        "sunup": false
      },
      "symbolCode": {
        "next1Hour": "clearsky_night",
        "next6Hours": "fair_day",
        "next12Hours": "lightrainshowers_day"
      },
      "precipitation": {
        "value": 0
      },
      "temperature": {
        "value": 2.2
      },
      "wind": {
        "direction": 269,
        "speed": 0.7
      },
      "feelsLike": {
        "value": 2.2
      },
      "pressure": {
        "value": 1023
      },
      "uvIndex": {
        "value": 0
      },
      "cloudCover": {
        "value": 2,
        "high": 0,
        "middle": 1,
        "low": 0,
        "fog": 0
      },
      "humidity": {
        "value": 84.4
      },
      "dewPoint": {
        "value": -0.3
      },
      "start": "2025-12-19T05:00:00+01:00",
      "end": "2025-12-19T06:00:00+01:00"
    },
    {
      "symbol": {
        "n": 2,
        "clouds": 1,
        "precip": 0,
        "var": "Moon",
        "sunup": false
      },
      "symbolCode": {
        "next1Hour": "fair_night",
        "next6Hours": "fair_day",
        "next12Hours": "lightrainshowers_day"
      },
      "precipitation": {
        "value": 0
      },
      "temperature": {
        "value": 2
      },
      "wind": {
        "direction": 274,
        "speed": 0.7
      },
      "feelsLike": {
        "value": 2
      },
      "pressure": {
        "value": 1023
      },
      "uvIndex": {
        "value": 0
      },
      "cloudCover": {
        "value": 21,
        "high": 0,
        "middle": 1,
        "low": 20,
        "fog": 21
      },
      "humidity": {
        "value": 84.4
      },
      "dewPoint": {
        "value": -0.5
      },
      "start": "2025-12-19T06:00:00+01:00",
      "end": "2025-12-19T07:00:00+01:00"
    },
    {
      "symbol": {
        "n": 2,
        "clouds": 1,
        "precip": 0,
        "var": "Moon",
        "sunup": false
      },
      "symbolCode": {
        "next1Hour": "fair_night",
        "next6Hours": "fair_day",
        "next12Hours": "lightrainshowers_day"
      },
      "precipitation": {
        "value": 0
      },
      "temperature": {
        "value": 2.1
      },
      "wind": {
        "direction": 274,
        "speed": 0.7
      },
      "feelsLike": {
        "value": 2.1
      },
      "pressure": {
        "value": 1024
      },
      "uvIndex": {
        "value": 0
      },
      "cloudCover": {
        "value": 23,
        "high": 0,
        "middle": 0,
        "low": 23,
        "fog": 21
      },
      "humidity": {
        "value": 83.2
      },
      "dewPoint": {
        "value": -0.6
      },
      "start": "2025-12-19T07:00:00+01:00",
      "end": "2025-12-19T08:00:00+01:00"
    },
    {
      "symbol": {
        "n": 1,
        "clouds": 0,
        "precip": 0,
        "var": "Sun",
        "sunup": false
      },
      "symbolCode": {
        "next1Hour": "clearsky_day",
        "next6Hours": "fair_day",
        "next12Hours": "lightrainshowers_day"
      },
      "precipitation": {
        "value": 0
      },
      "temperature": {
        "value": 2.2
      },
      "wind": {
        "direction": 266,
        "speed": 0.6
      },
      "feelsLike": {
        "value": 2.2
      },
      "pressure": {
        "value": 1024
      },
      "uvIndex": {
        "value": 0
      },
      "cloudCover": {
        "value": 13,
        "high": 0,
        "middle": 1,
        "low": 12,
        "fog": 0
      },
      "humidity": {
        "value": 81.1
      },
      "dewPoint": {
        "value": -0.9
      },
      "start": "2025-12-19T08:00:00+01:00",
      "end": "2025-12-19T09:00:00+01:00"
    },
    {
      "symbol": {
        "n": 2,
        "clouds": 1,
        "precip": 0,
        "var": "Sun",
        "sunup": false
      },
      "symbolCode": {
        "next1Hour": "fair_day",
        "next6Hours": "fair_day",
        "next12Hours": "lightrainshowers_day"
      },
      "precipitation": {
        "value": 0
      },
      "temperature": {
        "value": 3
      },
      "wind": {
        "direction": 276,
        "speed": 0.7
      },
      "feelsLike": {
        "value": 3
      },
      "pressure": {
        "value": 1024
      },
      "uvIndex": {
        "value": 0.1
      },
      "cloudCover": {
        "value": 14,
        "high": 0,
        "middle": 6,
        "low": 9,
        "fog": 0
      },
      "humidity": {
        "value": 79.7
      },
      "dewPoint": {
        "value": -0.3
      },
      "start": "2025-12-19T09:00:00+01:00",
      "end": "2025-12-19T10:00:00+01:00"
    },
    {
      "symbol": {
        "n": 1,
        "clouds": 0,
        "precip": 0,
        "var": "Sun",
        "sunup": false
      },
      "symbolCode": {
        "next1Hour": "clearsky_day",
        "next6Hours": "partlycloudy_day",
        "next12Hours": "lightrainshowers_day"
      },
      "precipitation": {
        "value": 0
      },
      "temperature": {
        "value": 5.4
      },
      "wind": {
        "direction": 296,
        "speed": 1.5
      },
      "feelsLike": {
        "value": 4
      },
      "pressure": {
        "value": 1024
      },
      "uvIndex": {
        "value": 0.4
      },
      "cloudCover": {
        "value": 5,
        "high": 0,
        "middle": 1,
        "low": 5,
        "fog": 0
      },
      "humidity": {
        "value": 68.6
      },
      "dewPoint": {
        "value": -0.1
      },
      "start": "2025-12-19T10:00:00+01:00",
      "end": "2025-12-19T11:00:00+01:00"
    },
    {
      "symbol": {
        "n": 1,
        "clouds": 0,
        "precip": 0,
        "var": "Sun",
        "sunup": false
      },
      "symbolCode": {
        "next1Hour": "clearsky_day",
        "next6Hours": "rainshowers_day",
        "next12Hours": "rainshowers_day"
      },
      "precipitation": {
        "value": 0
      },
      "temperature": {
        "value": 6.7
      },
      "wind": {
        "direction": 311,
        "speed": 1.8
      },
      "feelsLike": {
        "value": 6
      },
      "pressure": {
        "value": 1024
      },
      "uvIndex": {
        "value": 0.8
      },
      "cloudCover": {
        "value": 4,
        "high": 0,
        "middle": 2,
        "low": 2,
        "fog": 0
      },
      "humidity": {
        "value": 67.9
      },
      "dewPoint": {
        "value": 1
      },
      "start": "2025-12-19T11:00:00+01:00",
      "end": "2025-12-19T12:00:00+01:00"
    },
    {
      "symbol": {
        "n": 2,
        "clouds": 1,
        "precip": 0,
        "var": "Sun",
        "sunup": false
      },
      "symbolCode": {
        "next1Hour": "fair_day",
        "next6Hours": "rainshowers_day",
        "next12Hours": "lightrainshowers_day"
      },
      "precipitation": {
        "value": 0
      },
      "temperature": {
        "value": 7.6
      },
      "wind": {
        "direction": 313,
        "speed": 1.6
      },
      "feelsLike": {
        "value": 7
      },
      "pressure": {
        "value": 1024
      },
      "uvIndex": {
        "value": 1
      },
      "cloudCover": {
        "value": 20,
        "high": 0,
        "middle": 17,
        "low": 10,
        "fog": 0
      },
      "humidity": {
        "value": 73.7
      },
      "dewPoint": {
        "value": 3.1
      },
      "start": "2025-12-19T12:00:00+01:00",
      "end": "2025-12-19T13:00:00+01:00"
    },
    {
      "symbol": {
        "n": 3,
        "clouds": 2,
        "precip": 0,
        "var": "Sun",
        "sunup": false
      },
      "symbolCode": {
        "next1Hour": "partlycloudy_day",
        "next6Hours": "rainshowers_day",
        "next12Hours": "lightrainshowers_day"
      },
      "precipitation": {
        "value": 0
      },
      "temperature": {
        "value": 8.3
      },
      "wind": {
        "direction": 345,
        "speed": 1.8
      },
      "feelsLike": {
        "value": 7
      },
      "pressure": {
        "value": 1023
      },
      "uvIndex": {
        "value": 0.9
      },
      "cloudCover": {
        "value": 41,
        "high": 0,
        "middle": 36,
        "low": 12,
        "fog": 0
      },
      "humidity": {
        "value": 73.2
      },
      "dewPoint": {
        "value": 3.7
      },
      "start": "2025-12-19T13:00:00+01:00",
      "end": "2025-12-19T14:00:00+01:00"
    },
    {
      "symbol": {
        "n": 3,
        "clouds": 2,
        "precip": 0,
        "var": "Sun",
        "sunup": false
      },
      "symbolCode": {
        "next1Hour": "partlycloudy_day",
        "next6Hours": "rainshowers_day",
        "next12Hours": "lightrain"
      },
      "precipitation": {
        "value": 0
      },
      "temperature": {
        "value": 8.5
      },
      "wind": {
        "direction": 302,
        "speed": 1.9
      },
      "feelsLike": {
        "value": 8
      },
      "pressure": {
        "value": 1023
      },
      "uvIndex": {
        "value": 0.6
      },
      "cloudCover": {
        "value": 52,
        "high": 0,
        "middle": 45,
        "low": 19,
        "fog": 0
      },
      "humidity": {
        "value": 74
      },
      "dewPoint": {
        "value": 4
      },
      "start": "2025-12-19T14:00:00+01:00",
      "end": "2025-12-19T15:00:00+01:00"
    },
    {
      "symbol": {
        "n": 40,
        "clouds": 2,
        "precipPhase": "Rain",
        "precip": 1,
        "var": "Sun",
        "sunup": false
      },
      "symbolCode": {
        "next1Hour": "lightrainshowers_day",
        "next6Hours": "rain",
        "next12Hours": "lightrain"
      },
      "precipitation": {
        "value": 0.1
      },
      "temperature": {
        "value": 7.6
      },
      "wind": {
        "direction": 305,
        "speed": 1.4
      },
      "feelsLike": {
        "value": 7
      },
      "pressure": {
        "value": 1023
      },
      "uvIndex": {
        "value": 0.3
      },
      "cloudCover": {
        "value": 31,
        "high": 0,
        "middle": 13,
        "low": 27,
        "fog": 0
      },
      "humidity": {
        "value": 82.9
      },
      "dewPoint": {
        "value": 4.8
      },
      "start": "2025-12-19T15:00:00+01:00",
      "end": "2025-12-19T16:00:00+01:00"
    },
    {
      "symbol": {
        "n": 41,
        "clouds": 2,
        "precipPhase": "Rain",
        "precip": 3,
        "var": "Sun",
        "sunup": false
      },
      "symbolCode": {
        "next1Hour": "heavyrainshowers_day",
        "next6Hours": "rain",
        "next12Hours": "lightrain"
      },
      "precipitation": {
        "value": 1.2
      },
      "temperature": {
        "value": 6.6
      },
      "wind": {
        "direction": 37,
        "speed": 0.9
      },
      "feelsLike": {
        "value": 6.6
      },
      "pressure": {
        "value": 1023
      },
      "uvIndex": {
        "value": 0.1
      },
      "cloudCover": {
        "value": 82,
        "high": 0,
        "middle": 80,
        "low": 47,
        "fog": 0
      },
      "humidity": {
        "value": 82
      },
      "dewPoint": {
        "value": 3.6
      },
      "start": "2025-12-19T16:00:00+01:00",
      "end": "2025-12-19T17:00:00+01:00"
    },
    {
      "symbol": {
        "n": 41,
        "clouds": 2,
        "precipPhase": "Rain",
        "precip": 3,
        "var": "Moon",
        "sunup": false
      },
      "symbolCode": {
        "next1Hour": "heavyrainshowers_night",
        "next6Hours": "rain",
        "next12Hours": "rain"
      },
      "precipitation": {
        "value": 1.4
      },
      "temperature": {
        "value": 5.7
      },
      "wind": {
        "direction": 297,
        "speed": 1.4
      },
      "feelsLike": {
        "value": 5
      },
      "pressure": {
        "value": 1023
      },
      "uvIndex": {
        "value": 0
      },
      "cloudCover": {
        "value": 74,
        "high": 0,
        "middle": 73,
        "low": 21,
        "fog": 0
      },
      "humidity": {
        "value": 83.8
      },
      "dewPoint": {
        "value": 3.1
      },
      "start": "2025-12-19T17:00:00+01:00",
      "end": "2025-12-19T18:00:00+01:00"
    },
    {
      "symbol": {
        "n": 46,
        "clouds": 3,
        "precipPhase": "Rain",
        "precip": 1,
        "sunup": false
      },
      "symbolCode": {
        "next1Hour": "lightrain",
        "next6Hours": "lightrain",
        "next12Hours": "lightrain"
      },
      "precipitation": {
        "value": 0.1
      },
      "temperature": {
        "value": 4.7
      },
      "wind": {
        "direction": 291,
        "speed": 1.6
      },
      "feelsLike": {
        "value": 3
      },
      "pressure": {
        "value": 1023
      },
      "uvIndex": {
        "value": 0
      },
      "cloudCover": {
        "value": 97,
        "high": 1,
        "middle": 97,
        "low": 48,
        "fog": 0
      },
      "humidity": {
        "value": 84.1
      },
      "dewPoint": {
        "value": 2.1
      },
      "start": "2025-12-19T18:00:00+01:00",
      "end": "2025-12-19T19:00:00+01:00"
    },
    {
      "symbol": {
        "n": 4,
        "clouds": 3,
        "precip": 0,
        "sunup": false
      },
      "symbolCode": {
        "next1Hour": "cloudy",
        "next6Hours": "lightrain",
        "next12Hours": "lightrain"
      },
      "precipitation": {
        "value": 0
      },
      "temperature": {
        "value": 5.5
      },
      "wind": {
        "direction": 301,
        "speed": 1
      },
      "feelsLike": {
        "value": 5.5
      },
      "pressure": {
        "value": 1023
      },
      "uvIndex": {
        "value": 0
      },
      "cloudCover": {
        "value": 95,
        "high": 2,
        "middle": 95,
        "low": 59,
        "fog": 0
      },
      "humidity": {
        "value": 84.2
      },
      "dewPoint": {
        "value": 2.9
      },
      "start": "2025-12-19T19:00:00+01:00",
      "end": "2025-12-19T20:00:00+01:00"
    },
    {
      "symbol": {
        "n": 46,
        "clouds": 3,
        "precipPhase": "Rain",
        "precip": 1,
        "sunup": false
      },
      "symbolCode": {
        "next1Hour": "lightrain",
        "next6Hours": "lightrain",
        "next12Hours": "lightrain"
      },
      "precipitation": {
        "value": 0.2
      },
      "temperature": {
        "value": 5.6
      },
      "wind": {
        "direction": 262,
        "speed": 1.1
      },
      "feelsLike": {
        "value": 5.6
      },
      "pressure": {
        "value": 1023
      },
      "uvIndex": {
        "value": 0
      },
      "cloudCover": {
        "value": 100,
        "high": 0,
        "middle": 100,
        "low": 77,
        "fog": 0
      },
      "humidity": {
        "value": 84.8
      },
      "dewPoint": {
        "value": 3.1
      },
      "start": "2025-12-19T20:00:00+01:00",
      "end": "2025-12-19T21:00:00+01:00"
    },
    {
      "symbol": {
        "n": 46,
        "clouds": 3,
        "precipPhase": "Rain",
        "precip": 1,
        "sunup": false
      },
      "symbolCode": {
        "next1Hour": "lightrain",
        "next6Hours": "lightrain",
        "next12Hours": "lightrain"
      },
      "precipitation": {
        "value": 0.2
      },
      "temperature": {
        "value": 5.7
      },
      "wind": {
        "direction": 329,
        "speed": 1.6
      },
      "feelsLike": {
        "value": 5
      },
      "pressure": {
        "value": 1023
      },
      "uvIndex": {
        "value": 0
      },
      "cloudCover": {
        "value": 99,
        "high": 0,
        "middle": 99,
        "low": 77,
        "fog": 0
      },
      "humidity": {
        "value": 85.2
      },
      "dewPoint": {
        "value": 3.3
      },
      "start": "2025-12-19T21:00:00+01:00",
      "end": "2025-12-19T22:00:00+01:00"
    },
    {
      "symbol": {
        "n": 9,
        "clouds": 3,
        "precipPhase": "Rain",
        "precip": 2,
        "sunup": false
      },
      "symbolCode": {
        "next1Hour": "rain",
        "next6Hours": "lightrain",
        "next12Hours": "lightrain"
      },
      "precipitation": {
        "value": 0.3
      },
      "temperature": {
        "value": 5.8
      },
      "wind": {
        "direction": 323,
        "speed": 1.5
      },
      "feelsLike": {
        "value": 5
      },
      "pressure": {
        "value": 1023
      },
      "uvIndex": {
        "value": 0
      },
      "cloudCover": {
        "value": 100,
        "high": 0,
        "middle": 100,
        "low": 99,
        "fog": 0
      },
      "humidity": {
        "value": 85.6
      },
      "dewPoint": {
        "value": 3.5
      },
      "start": "2025-12-19T22:00:00+01:00",
      "end": "2025-12-19T23:00:00+01:00"
    },
    {
      "symbol": {
        "n": 4,
        "clouds": 3,
        "precip": 0,
        "sunup": false
      },
      "symbolCode": {
        "next1Hour": "cloudy",
        "next6Hours": "rain",
        "next12Hours": "lightrain"
      },
      "precipitation": {
        "value": 0
      },
      "temperature": {
        "value": 6
      },
      "wind": {
        "direction": 293,
        "speed": 1
      },
      "feelsLike": {
        "value": 6
      },
      "pressure": {
        "value": 1022
      },
      "uvIndex": {
        "value": 0
      },
      "cloudCover": {
        "value": 92,
        "high": 0,
        "middle": 89,
        "low": 56,
        "fog": 0
      },
      "humidity": {
        "value": 85.3
      },
      "dewPoint": {
        "value": 3.6
      },
      "start": "2025-12-19T23:00:00+01:00",
      "end": "2025-12-20T00:00:00+01:00"
    },
    {
      "symbol": {
        "n": 3,
        "clouds": 2,
        "precip": 0,
        "var": "Moon",
        "sunup": false
      },
      "symbolCode": {
        "next1Hour": "partlycloudy_night",
        "next6Hours": "rain",
        "next12Hours": "lightrain"
      },
      "precipitation": {
        "value": 0
      },
      "temperature": {
        "value": 5.6
      },
      "wind": {
        "direction": 13,
        "speed": 1.3
      },
      "feelsLike": {
        "value": 5.6
      },
      "pressure": {
        "value": 1022
      },
      "uvIndex": {
        "value": 0
      },
      "cloudCover": {
        "value": 81,
        "high": 0,
        "middle": 81,
        "low": 2,
        "fog": 0
      },
      "humidity": {
        "value": 86.6
      },
      "dewPoint": {
        "value": 3.4
      },
      "start": "2025-12-20T00:00:00+01:00",
      "end": "2025-12-20T01:00:00+01:00"
    },
    {
      "symbol": {
        "n": 4,
        "clouds": 3,
        "precip": 0,
        "sunup": false
      },
      "symbolCode": {
        "next1Hour": "cloudy",
        "next6Hours": "rain",
        "next12Hours": "lightrain"
      },
      "precipitation": {
        "value": 0
      },
      "temperature": {
        "value": 5.1
      },
      "wind": {
        "direction": 321,
        "speed": 1.6
      },
      "feelsLike": {
        "value": 4
      },
      "pressure": {
        "value": 1021
      },
      "uvIndex": {
        "value": 0
      },
      "cloudCover": {
        "value": 93,
        "high": 0,
        "middle": 93,
        "low": 2,
        "fog": 0
      },
      "humidity": {
        "value": 87.8
      },
      "dewPoint": {
        "value": 3.1
      },
      "start": "2025-12-20T01:00:00+01:00",
      "end": "2025-12-20T02:00:00+01:00"
    },
    {
      "symbol": {
        "n": 9,
        "clouds": 3,
        "precipPhase": "Rain",
        "precip": 2,
        "sunup": false
      },
      "symbolCode": {
        "next1Hour": "rain",
        "next6Hours": "rain",
        "next12Hours": "lightrain"
      },
      "precipitation": {
        "value": 0.3
      },
      "temperature": {
        "value": 5.3
      },
      "wind": {
        "direction": 327,
        "speed": 1.1
      },
      "feelsLike": {
        "value": 5.3
      },
      "pressure": {
        "value": 1020
      },
      "uvIndex": {
        "value": 0
      },
      "cloudCover": {
        "value": 91,
        "high": 11,
        "middle": 90,
        "low": 4,
        "fog": 0
      },
      "humidity": {
        "value": 86.7
      },
      "dewPoint": {
        "value": 3.1
      },
      "start": "2025-12-20T02:00:00+01:00",
      "end": "2025-12-20T03:00:00+01:00"
    },
    {
      "symbol": {
        "n": 9,
        "clouds": 3,
        "precipPhase": "Rain",
        "precip": 2,
        "sunup": false
      },
      "symbolCode": {
        "next1Hour": "rain",
        "next6Hours": "rain",
        "next12Hours": "lightrain"
      },
      "precipitation": {
        "value": 0.4
      },
      "temperature": {
        "value": 4.9
      },
      "wind": {
        "direction": 260,
        "speed": 1.1
      },
      "feelsLike": {
        "value": 4.9
      },
      "pressure": {
        "value": 1020
      },
      "uvIndex": {
        "value": 0
      },
      "cloudCover": {
        "value": 99,
        "high": 2,
        "middle": 99,
        "low": 15,
        "fog": 0
      },
      "humidity": {
        "value": 87
      },
      "dewPoint": {
        "value": 2.8
      },
      "start": "2025-12-20T03:00:00+01:00",
      "end": "2025-12-20T04:00:00+01:00"
    },
    {
      "symbol": {
        "n": 10,
        "clouds": 3,
        "precipPhase": "Rain",
        "precip": 3,
        "sunup": false
      },
      "symbolCode": {
        "next1Hour": "heavyrain",
        "next6Hours": "rain",
        "next12Hours": "lightrain"
      },
      "precipitation": {
        "value": 1
      },
      "temperature": {
        "value": 5.2
      },
      "wind": {
        "direction": 290,
        "speed": 1
      },
      "feelsLike": {
        "value": 5.2
      },
      "pressure": {
        "value": 1019
      },
      "uvIndex": {
        "value": 0
      },
      "cloudCover": {
        "value": 99,
        "high": 29,
        "middle": 99,
        "low": 19,
        "fog": 0
      },
      "humidity": {
        "value": 87.9
      },
      "dewPoint": {
        "value": 3.2
      },
      "start": "2025-12-20T04:00:00+01:00",
      "end": "2025-12-20T05:00:00+01:00"
    },
    {
      "symbol": {
        "n": 4,
        "clouds": 3,
        "precip": 0,
        "sunup": false
      },
      "symbolCode": {
        "next1Hour": "cloudy",
        "next6Hours": "partlycloudy_day",
        "next12Hours": "cloudy"
      },
      "precipitation": {
        "value": 0
      },
      "temperature": {
        "value": 5.1
      },
      "wind": {
        "direction": 347,
        "speed": 1.1
      },
      "feelsLike": {
        "value": 5.1
      },
      "pressure": {
        "value": 1019
      },
      "uvIndex": {
        "value": 0
      },
      "cloudCover": {
        "value": 100,
        "high": 42,
        "middle": 100,
        "low": 40,
        "fog": 0
      },
      "humidity": {
        "value": 89.4
      },
      "dewPoint": {
        "value": 3.4
      },
      "start": "2025-12-20T05:00:00+01:00",
      "end": "2025-12-20T06:00:00+01:00"
    },
    {
      "symbol": {
        "n": 4,
        "clouds": 3,
        "precip": 0,
        "sunup": false
      },
      "symbolCode": {
        "next1Hour": "cloudy",
        "next6Hours": "partlycloudy_day",
        "next12Hours": "cloudy"
      },
      "precipitation": {
        "value": 0
      },
      "temperature": {
        "value": 5
      },
      "wind": {
        "direction": 288,
        "speed": 1.1
      },
      "feelsLike": {
        "value": 5
      },
      "pressure": {
        "value": 1019
      },
      "uvIndex": {
        "value": 0
      },
      "cloudCover": {
        "value": 89,
        "high": 20,
        "middle": 88,
        "low": 24,
        "fog": 0
      },
      "humidity": {
        "value": 90.9
      },
      "dewPoint": {
        "value": 3.5
      },
      "start": "2025-12-20T06:00:00+01:00",
      "end": "2025-12-20T07:00:00+01:00"
    },
    {
      "symbol": {
        "n": 3,
        "clouds": 2,
        "precip": 0,
        "var": "Moon",
        "sunup": false
      },
      "symbolCode": {
        "next1Hour": "partlycloudy_night",
        "next6Hours": "cloudy",
        "next12Hours": "cloudy"
      },
      "precipitation": {
        "value": 0
      },
      "temperature": {
        "value": 4.7
      },
      "wind": {
        "direction": 339,
        "speed": 1.4
      },
      "feelsLike": {
        "value": 4
      },
      "pressure": {
        "value": 1018
      },
      "uvIndex": {
        "value": 0
      },
      "cloudCover": {
        "value": 86,
        "high": 4,
        "middle": 85,
        "low": 16,
        "fog": 0
      },
      "humidity": {
        "value": 91.3
      },
      "dewPoint": {
        "value": 3.3
      },
      "start": "2025-12-20T07:00:00+01:00",
      "end": "2025-12-20T08:00:00+01:00"
    },
    {
      "symbol": {
        "n": 4,
        "clouds": 3,
        "precip": 0,
        "sunup": false
      },
      "symbolCode": {
        "next1Hour": "cloudy",
        "next6Hours": "cloudy"
      },
      "precipitation": {
        "value": 0
      },
      "temperature": {
        "value": 4.7
      },
      "wind": {
        "direction": 253,
        "speed": 1.2
      },
      "feelsLike": {
        "value": 4.7
      },
      "pressure": {
        "value": 1019
      },
      "uvIndex": {
        "value": 0
      },
      "cloudCover": {
        "value": 100,
        "high": 48,
        "middle": 100,
        "low": 2,
        "fog": 0
      },
      "humidity": {
        "value": 92.3
      },
      "dewPoint": {
        "value": 3.4
      },
      "start": "2025-12-20T08:00:00+01:00",
      "end": "2025-12-20T09:00:00+01:00"
    },
    {
      "symbol": {
        "n": 4,
        "clouds": 3,
        "precip": 0,
        "sunup": false
      },
      "symbolCode": {
        "next1Hour": "cloudy",
        "next6Hours": "cloudy"
      },
      "precipitation": {
        "value": 0
      },
      "temperature": {
        "value": 5
      },
      "wind": {
        "direction": 281,
        "speed": 1.2
      },
      "feelsLike": {
        "value": 5
      },
      "pressure": {
        "value": 1018
      },
      "uvIndex": {
        "value": 0.1
      },
      "cloudCover": {
        "value": 93,
        "high": 4,
        "middle": 93,
        "low": 3,
        "fog": 0
      },
      "humidity": {
        "value": 92.6
      },
      "dewPoint": {
        "value": 3.8
      },
      "start": "2025-12-20T09:00:00+01:00",
      "end": "2025-12-20T10:00:00+01:00"
    },
    {
      "symbol": {
        "n": 3,
        "clouds": 2,
        "precip": 0,
        "var": "Sun",
        "sunup": false
      },
      "symbolCode": {
        "next1Hour": "partlycloudy_day",
        "next6Hours": "cloudy"
      },
      "precipitation": {
        "value": 0
      },
      "temperature": {
        "value": 5.2
      },
      "wind": {
        "direction": 286,
        "speed": 1.3
      },
      "feelsLike": {
        "value": 5.2
      },
      "pressure": {
        "value": 1018
      },
      "uvIndex": {
        "value": 0.4
      },
      "cloudCover": {
        "value": 67,
        "high": 0,
        "middle": 67,
        "low": 7,
        "fog": 0
      },
      "humidity": {
        "value": 93
      },
      "dewPoint": {
        "value": 4.1
      },
      "start": "2025-12-20T10:00:00+01:00",
      "end": "2025-12-20T11:00:00+01:00"
    },
    {
      "symbol": {
        "n": 3,
        "clouds": 2,
        "precip": 0,
        "var": "Sun",
        "sunup": false
      },
      "symbolCode": {
        "next1Hour": "partlycloudy_day",
        "next6Hours": "cloudy"
      },
      "precipitation": {
        "value": 0
      },
      "temperature": {
        "value": 6.1
      },
      "wind": {
        "direction": 270,
        "speed": 1.4
      },
      "feelsLike": {
        "value": 5
      },
      "pressure": {
        "value": 1018
      },
      "uvIndex": {
        "value": 0.7
      },
      "cloudCover": {
        "value": 58,
        "high": 16,
        "middle": 57,
        "low": 0,
        "fog": 0
      },
      "humidity": {
        "value": 91.5
      },
      "dewPoint": {
        "value": 4.7
      },
      "start": "2025-12-20T11:00:00+01:00",
      "end": "2025-12-20T12:00:00+01:00"
    },
    {
      "symbol": {
        "n": 4,
        "clouds": 3,
        "precip": 0,
        "sunup": false
      },
      "symbolCode": {
        "next1Hour": "cloudy",
        "next6Hours": "cloudy"
      },
      "precipitation": {
        "value": 0
      },
      "temperature": {
        "value": 7.8
      },
      "wind": {
        "direction": 266,
        "speed": 1.2
      },
      "feelsLike": {
        "value": 7.8
      },
      "pressure": {
        "value": 1017
      },
      "uvIndex": {
        "value": 1
      },
      "cloudCover": {
        "value": 100,
        "high": 24,
        "middle": 100,
        "low": 1,
        "fog": 0
      },
      "humidity": {
        "value": 92.4
      },
      "dewPoint": {
        "value": 6.6
      },
      "start": "2025-12-20T12:00:00+01:00",
      "end": "2025-12-20T13:00:00+01:00"
    },
    {
      "symbol": {
        "n": 4,
        "clouds": 3,
        "precip": 0,
        "sunup": false
      },
      "symbolCode": {
        "next1Hour": "cloudy",
        "next6Hours": "cloudy",
        "next12Hours": "lightrain"
      },
      "precipitation": {
        "value": 0
      },
      "temperature": {
        "value": 7.9
      },
      "wind": {
        "direction": 254,
        "speed": 1.3
      },
      "feelsLike": {
        "value": 7.9
      },
      "pressure": {
        "value": 1016
      },
      "uvIndex": {
        "value": 1
      },
      "cloudCover": {
        "value": 100,
        "high": 41,
        "middle": 100,
        "low": 1,
        "fog": 0
      },
      "humidity": {
        "value": 92.1
      },
      "dewPoint": {
        "value": 6.7
      },
      "start": "2025-12-20T13:00:00+01:00",
      "end": "2025-12-20T14:00:00+01:00"
    },
    {
      "symbol": {
        "n": 4,
        "clouds": 3,
        "precip": 0,
        "sunup": false
      },
      "symbolCode": {
        "next1Hour": "cloudy"
      },
      "precipitation": {
        "value": 0
      },
      "temperature": {
        "value": 7.1
      },
      "wind": {
        "direction": 307,
        "speed": 1.3
      },
      "feelsLike": {
        "value": 7.1
      },
      "pressure": {
        "value": 1016
      },
      "uvIndex": {
        "value": 0.7
      },
      "cloudCover": {
        "value": 100,
        "high": 33,
        "middle": 100,
        "low": 0,
        "fog": 0
      },
      "humidity": {
        "value": 95.5
      },
      "dewPoint": {
        "value": 6.4
      },
      "start": "2025-12-20T14:00:00+01:00",
      "end": "2025-12-20T15:00:00+01:00"
    },
    {
      "symbol": {
        "n": 4,
        "clouds": 3,
        "precip": 0,
        "sunup": false
      },
      "symbolCode": {
        "next1Hour": "cloudy"
      },
      "precipitation": {
        "value": 0
      },
      "temperature": {
        "value": 6.7
      },
      "wind": {
        "direction": 309,
        "speed": 1.9
      },
      "feelsLike": {
        "value": 5
      },
      "pressure": {
        "value": 1015
      },
      "uvIndex": {
        "value": 0.4
      },
      "cloudCover": {
        "value": 97,
        "high": 72,
        "middle": 95,
        "low": 1,
        "fog": 0
      },
      "humidity": {
        "value": 96.3
      },
      "dewPoint": {
        "value": 6.1
      },
      "start": "2025-12-20T15:00:00+01:00",
      "end": "2025-12-20T16:00:00+01:00"
    },
    {
      "symbol": {
        "n": 4,
        "clouds": 3,
        "precip": 0,
        "sunup": false
      },
      "symbolCode": {
        "next1Hour": "cloudy"
      },
      "precipitation": {
        "value": 0
      },
      "temperature": {
        "value": 6.5
      },
      "wind": {
        "direction": 307,
        "speed": 1.3
      },
      "feelsLike": {
        "value": 6.5
      },
      "pressure": {
        "value": 1015
      },
      "uvIndex": {
        "value": 0.1
      },
      "cloudCover": {
        "value": 98,
        "high": 73,
        "middle": 98,
        "low": 3,
        "fog": 0
      },
      "humidity": {
        "value": 95.7
      },
      "dewPoint": {
        "value": 5.8
      },
      "start": "2025-12-20T16:00:00+01:00",
      "end": "2025-12-20T17:00:00+01:00"
    },
    {
      "symbol": {
        "n": 15,
        "clouds": 3,
        "precip": 0,
        "sunup": false
      },
      "symbolCode": {
        "next1Hour": "fog"
      },
      "precipitation": {
        "value": 0
      },
      "temperature": {
        "value": 6.1
      },
      "wind": {
        "direction": 340,
        "speed": 1.3
      },
      "feelsLike": {
        "value": 6.1
      },
      "pressure": {
        "value": 1015
      },
      "uvIndex": {
        "value": 0
      },
      "cloudCover": {
        "value": 100,
        "high": 99,
        "middle": 94,
        "low": 32,
        "fog": 31
      },
      "humidity": {
        "value": 95
      },
      "dewPoint": {
        "value": 5.3
      },
      "start": "2025-12-20T17:00:00+01:00",
      "end": "2025-12-20T18:00:00+01:00"
    },
    {
      "symbol": {
        "n": 15,
        "clouds": 3,
        "precip": 0,
        "sunup": false
      },
      "symbolCode": {
        "next1Hour": "fog"
      },
      "precipitation": {
        "value": 0
      },
      "temperature": {
        "value": 5.8
      },
      "wind": {
        "direction": 328,
        "speed": 1.4
      },
      "feelsLike": {
        "value": 5
      },
      "pressure": {
        "value": 1014
      },
      "uvIndex": {
        "value": 0
      },
      "cloudCover": {
        "value": 100,
        "high": 98,
        "middle": 100,
        "low": 27,
        "fog": 27
      },
      "humidity": {
        "value": 95.2
      },
      "dewPoint": {
        "value": 5
      },
      "start": "2025-12-20T18:00:00+01:00",
      "end": "2025-12-20T19:00:00+01:00"
    }
  ],
  "longIntervals": [
    {
      "symbol": {
        "n": 15,
        "clouds": 3,
        "precip": 0,
        "sunup": false
      },
      "symbolCode": {
        "next1Hour": "fog",
        "next6Hours": "fog",
        "next12Hours": "fair_day"
      },
      "precipitation": {
        "value": 0
      },
      "temperature": {
        "value": 1.6,
        "min": 2.3,
        "max": 7.6
      },
      "wind": {
        "direction": 223,
        "speed": 1.4
      },
      "feelsLike": {
        "value": 0
      },
      "pressure": {
        "value": 1026
      },
      "cloudCover": {
        "value": 99,
        "high": 97,
        "middle": 0,
        "low": 63,
        "fog": 40
      },
      "humidity": {
        "value": 93.9
      },
      "dewPoint": {
        "value": 0.6
      },
      "start": "2025-12-18T08:00:00+01:00",
      "end": "2025-12-18T12:00:00+01:00",
      "nominalStart": "2025-12-18T06:00:00+01:00",
      "nominalEnd": "2025-12-18T12:00:00+01:00"
    },
    {
      "symbol": {
        "n": 2,
        "clouds": 1,
        "precip": 0,
        "var": "Sun",
        "sunup": false
      },
      "symbolCode": {
        "next1Hour": "fog",
        "next6Hours": "fair_day",
        "next12Hours": "clearsky_day"
      },
      "precipitation": {
        "value": 0
      },
      "temperature": {
        "value": 6,
        "min": 3.4,
        "max": 7.6
      },
      "wind": {
        "direction": 261,
        "speed": 1.8
      },
      "feelsLike": {
        "value": 5
      },
      "pressure": {
        "value": 1026
      },
      "cloudCover": {
        "value": 55,
        "high": 3,
        "middle": 0,
        "low": 54,
        "fog": 28
      },
      "humidity": {
        "value": 93.6
      },
      "dewPoint": {
        "value": 5
      },
      "start": "2025-12-18T12:00:00+01:00",
      "end": "2025-12-18T18:00:00+01:00",
      "nominalStart": "2025-12-18T12:00:00+01:00",
      "nominalEnd": "2025-12-18T18:00:00+01:00"
    },
    {
      "symbol": {
        "n": 1,
        "clouds": 0,
        "precip": 0,
        "var": "Moon",
        "sunup": false
      },
      "symbolCode": {
        "next1Hour": "clearsky_night",
        "next6Hours": "clearsky_night",
        "next12Hours": "clearsky_night"
      },
      "precipitation": {
        "value": 0
      },
      "temperature": {
        "value": 3.4,
        "min": 2.5,
        "max": 3.5
      },
      "wind": {
        "direction": 250,
        "speed": 0.8
      },
      "feelsLike": {
        "value": 3.4
      },
      "pressure": {
        "value": 1022
      },
      "cloudCover": {
        "value": 2,
        "high": 0,
        "middle": 0,
        "low": 2,
        "fog": 0
      },
      "humidity": {
        "value": 89.5
      },
      "dewPoint": {
        "value": 1.7
      },
      "start": "2025-12-18T18:00:00+01:00",
      "end": "2025-12-19T00:00:00+01:00",
      "nominalStart": "2025-12-18T18:00:00+01:00",
      "nominalEnd": "2025-12-19T00:00:00+01:00"
    },
    {
      "symbol": {
        "n": 1,
        "clouds": 0,
        "precip": 0,
        "var": "Moon",
        "sunup": false
      },
      "symbolCode": {
        "next1Hour": "clearsky_night",
        "next6Hours": "clearsky_night",
        "next12Hours": "clearsky_day"
      },
      "precipitation": {
        "value": 0
      },
      "temperature": {
        "value": 2.5,
        "min": 2,
        "max": 2.3
      },
      "wind": {
        "direction": 249,
        "speed": 0.6
      },
      "feelsLike": {
        "value": 2.5
      },
      "pressure": {
        "value": 1023
      },
      "cloudCover": {
        "value": 1,
        "high": 0,
        "middle": 0,
        "low": 0,
        "fog": 0
      },
      "humidity": {
        "value": 85.1
      },
      "dewPoint": {
        "value": 0.1
      },
      "start": "2025-12-19T00:00:00+01:00",
      "end": "2025-12-19T06:00:00+01:00",
      "nominalStart": "2025-12-19T00:00:00+01:00",
      "nominalEnd": "2025-12-19T06:00:00+01:00"
    },
    {
      "symbol": {
        "n": 2,
        "clouds": 1,
        "precip": 0,
        "var": "Sun",
        "sunup": false
      },
      "symbolCode": {
        "next1Hour": "fair_night",
        "next6Hours": "fair_day",
        "next12Hours": "lightrainshowers_day"
      },
      "precipitation": {
        "value": 0
      },
      "temperature": {
        "value": 2,
        "min": 2.1,
        "max": 7.6
      },
      "wind": {
        "direction": 274,
        "speed": 0.7
      },
      "feelsLike": {
        "value": 2
      },
      "pressure": {
        "value": 1023
      },
      "cloudCover": {
        "value": 21,
        "high": 0,
        "middle": 1,
        "low": 20,
        "fog": 21
      },
      "humidity": {
        "value": 84.4
      },
      "dewPoint": {
        "value": -0.5
      },
      "start": "2025-12-19T06:00:00+01:00",
      "end": "2025-12-19T12:00:00+01:00",
      "nominalStart": "2025-12-19T06:00:00+01:00",
      "nominalEnd": "2025-12-19T12:00:00+01:00"
    },
    {
      "symbol": {
        "n": 5,
        "clouds": 2,
        "precipPhase": "Rain",
        "precip": 2,
        "var": "Sun",
        "sunup": false
      },
      "symbolCode": {
        "next1Hour": "fair_day",
        "next6Hours": "rainshowers_day",
        "next12Hours": "lightrainshowers_day"
      },
      "precipitation": {
        "value": 2.7
      },
      "temperature": {
        "value": 7.6,
        "min": 4.7,
        "max": 8.5
      },
      "wind": {
        "direction": 313,
        "speed": 1.6
      },
      "feelsLike": {
        "value": 7
      },
      "pressure": {
        "value": 1024
      },
      "cloudCover": {
        "value": 20,
        "high": 0,
        "middle": 17,
        "low": 10,
        "fog": 0
      },
      "humidity": {
        "value": 73.7
      },
      "dewPoint": {
        "value": 3.1
      },
      "start": "2025-12-19T12:00:00+01:00",
      "end": "2025-12-19T18:00:00+01:00",
      "nominalStart": "2025-12-19T12:00:00+01:00",
      "nominalEnd": "2025-12-19T18:00:00+01:00"
    },
    {
      "symbol": {
        "n": 46,
        "clouds": 3,
        "precipPhase": "Rain",
        "precip": 1,
        "sunup": false
      },
      "symbolCode": {
        "next1Hour": "lightrain",
        "next6Hours": "lightrain",
        "next12Hours": "lightrain"
      },
      "precipitation": {
        "value": 0.8
      },
      "temperature": {
        "value": 4.7,
        "min": 5.5,
        "max": 6
      },
      "wind": {
        "direction": 291,
        "speed": 1.6
      },
      "feelsLike": {
        "value": 3
      },
      "pressure": {
        "value": 1023
      },
      "cloudCover": {
        "value": 97,
        "high": 1,
        "middle": 97,
        "low": 48,
        "fog": 0
      },
      "humidity": {
        "value": 84.1
      },
      "dewPoint": {
        "value": 2.1
      },
      "start": "2025-12-19T18:00:00+01:00",
      "end": "2025-12-20T00:00:00+01:00",
      "nominalStart": "2025-12-19T18:00:00+01:00",
      "nominalEnd": "2025-12-20T00:00:00+01:00"
    },
    {
      "symbol": {
        "n": 9,
        "clouds": 3,
        "precipPhase": "Rain",
        "precip": 2,
        "sunup": false
      },
      "symbolCode": {
        "next1Hour": "partlycloudy_night",
        "next6Hours": "rain",
        "next12Hours": "lightrain"
      },
      "precipitation": {
        "value": 1.7
      },
      "temperature": {
        "value": 5.6,
        "min": 4.9,
        "max": 5.3
      },
      "wind": {
        "direction": 13,
        "speed": 1.3
      },
      "feelsLike": {
        "value": 5.6
      },
      "pressure": {
        "value": 1022
      },
      "cloudCover": {
        "value": 81,
        "high": 0,
        "middle": 81,
        "low": 2,
        "fog": 0
      },
      "humidity": {
        "value": 86.6
      },
      "dewPoint": {
        "value": 3.4
      },
      "start": "2025-12-20T00:00:00+01:00",
      "end": "2025-12-20T06:00:00+01:00",
      "nominalStart": "2025-12-20T00:00:00+01:00",
      "nominalEnd": "2025-12-20T06:00:00+01:00"
    },
    {
      "symbol": {
        "n": 3,
        "clouds": 2,
        "precip": 0,
        "var": "Sun",
        "sunup": false
      },
      "symbolCode": {
        "next1Hour": "cloudy",
        "next6Hours": "partlycloudy_day",
        "next12Hours": "cloudy"
      },
      "precipitation": {
        "value": 0.1
      },
      "temperature": {
        "value": 5,
        "min": 4.7,
        "max": 7.8
      },
      "wind": {
        "direction": 288,
        "speed": 1.1
      },
      "feelsLike": {
        "value": 5
      },
      "pressure": {
        "value": 1019
      },
      "cloudCover": {
        "value": 89,
        "high": 20,
        "middle": 88,
        "low": 24,
        "fog": 0
      },
      "humidity": {
        "value": 90.9
      },
      "dewPoint": {
        "value": 3.5
      },
      "start": "2025-12-20T06:00:00+01:00",
      "end": "2025-12-20T12:00:00+01:00",
      "nominalStart": "2025-12-20T06:00:00+01:00",
      "nominalEnd": "2025-12-20T12:00:00+01:00"
    },
    {
      "symbol": {
        "n": 4,
        "clouds": 3,
        "precip": 0,
        "sunup": false
      },
      "symbolCode": {
        "next1Hour": "cloudy",
        "next6Hours": "cloudy"
      },
      "precipitation": {
        "value": 0.1
      },
      "temperature": {
        "value": 7.8,
        "min": 5.8,
        "max": 7.9
      },
      "wind": {
        "direction": 266,
        "speed": 1.2
      },
      "feelsLike": {
        "value": 7.8
      },
      "pressure": {
        "value": 1017
      },
      "cloudCover": {
        "value": 100,
        "high": 24,
        "middle": 100,
        "low": 1,
        "fog": 0
      },
      "humidity": {
        "value": 92.4
      },
      "dewPoint": {
        "value": 6.6
      },
      "start": "2025-12-20T12:00:00+01:00",
      "end": "2025-12-20T18:00:00+01:00",
      "nominalStart": "2025-12-20T12:00:00+01:00",
      "nominalEnd": "2025-12-20T18:00:00+01:00"
    },
    {
      "symbol": {
        "n": 9,
        "clouds": 3,
        "precipPhase": "Rain",
        "precip": 2,
        "sunup": false
      },
      "symbolCode": {
        "next6Hours": "rain",
        "next12Hours": "lightrain"
      },
      "precipitation": {
        "value": 1.7
      },
      "temperature": {
        "value": 5.5,
        "min": 4.9,
        "max": 5.6
      },
      "wind": {
        "direction": 317,
        "speed": 1.4
      },
      "feelsLike": {
        "value": 5
      },
      "pressure": {
        "value": 1014
      },
      "uvIndex": {
        "value": 0
      },
      "cloudCover": {
        "value": 100,
        "high": 98,
        "middle": 100,
        "low": 30,
        "fog": 22
      },
      "humidity": {
        "value": 95.4
      },
      "dewPoint": {
        "value": 4.7
      },
      "start": "2025-12-20T19:00:00+01:00",
      "end": "2025-12-21T01:00:00+01:00",
      "nominalStart": "2025-12-20T18:00:00+01:00",
      "nominalEnd": "2025-12-21T00:00:00+01:00"
    },
    {
      "symbol": {
        "n": 4,
        "clouds": 3,
        "precip": 0,
        "sunup": false
      },
      "symbolCode": {
        "next6Hours": "cloudy",
        "next12Hours": "cloudy"
      },
      "precipitation": {
        "value": 0.3
      },
      "temperature": {
        "value": 5.3,
        "min": 5.2,
        "max": 5.6
      },
      "wind": {
        "direction": 334,
        "speed": 0.4
      },
      "feelsLike": {
        "value": 5.3
      },
      "pressure": {
        "value": 1012
      },
      "cloudCover": {
        "value": 100,
        "high": 100,
        "middle": 100,
        "low": 5,
        "fog": 0
      },
      "humidity": {
        "value": 93.4
      },
      "dewPoint": {
        "value": 4.2
      },
      "start": "2025-12-21T01:00:00+01:00",
      "end": "2025-12-21T07:00:00+01:00",
      "nominalStart": "2025-12-21T00:00:00+01:00",
      "nominalEnd": "2025-12-21T06:00:00+01:00"
    },
    {
      "symbol": {
        "n": 4,
        "clouds": 3,
        "precip": 0,
        "sunup": false
      },
      "symbolCode": {
        "next6Hours": "cloudy",
        "next12Hours": "lightrain"
      },
      "precipitation": {
        "value": 0.2
      },
      "temperature": {
        "value": 5.4,
        "min": 5.3,
        "max": 6.9
      },
      "wind": {
        "direction": 319,
        "speed": 0.4
      },
      "feelsLike": {
        "value": 5.4
      },
      "pressure": {
        "value": 1008
      },
      "cloudCover": {
        "value": 100,
        "high": 100,
        "middle": 98,
        "low": 1,
        "fog": 0
      },
      "humidity": {
        "value": 90.7
      },
      "dewPoint": {
        "value": 3.9
      },
      "start": "2025-12-21T07:00:00+01:00",
      "end": "2025-12-21T13:00:00+01:00",
      "nominalStart": "2025-12-21T06:00:00+01:00",
      "nominalEnd": "2025-12-21T12:00:00+01:00"
    },
    {
      "symbol": {
        "n": 9,
        "clouds": 3,
        "precipPhase": "Rain",
        "precip": 2,
        "sunup": false
      },
      "symbolCode": {
        "next6Hours": "rain",
        "next12Hours": "lightrain"
      },
      "precipitation": {
        "value": 2.1
      },
      "temperature": {
        "value": 6.4,
        "min": 4.6,
        "max": 6.5
      },
      "wind": {
        "direction": 282,
        "speed": 0.1
      },
      "feelsLike": {
        "value": 6.4
      },
      "pressure": {
        "value": 1007
      },
      "cloudCover": {
        "value": 100,
        "high": 99,
        "middle": 100,
        "low": 0,
        "fog": 0
      },
      "humidity": {
        "value": 87.4
      },
      "dewPoint": {
        "value": 4.4
      },
      "start": "2025-12-21T13:00:00+01:00",
      "end": "2025-12-21T19:00:00+01:00",
      "nominalStart": "2025-12-21T12:00:00+01:00",
      "nominalEnd": "2025-12-21T18:00:00+01:00"
    },
    {
      "symbol": {
        "n": 4,
        "clouds": 3,
        "precip": 0,
        "sunup": false
      },
      "symbolCode": {
        "next6Hours": "cloudy",
        "next12Hours": "cloudy"
      },
      "precipitation": {
        "value": 0.1
      },
      "temperature": {
        "value": 4.9,
        "min": 4.2,
        "max": 4.9
      },
      "wind": {
        "direction": 252,
        "speed": 0.4
      },
      "feelsLike": {
        "value": 4.9
      },
      "pressure": {
        "value": 1006
      },
      "cloudCover": {
        "value": 100,
        "high": 100,
        "middle": 79,
        "low": 0,
        "fog": 0
      },
      "humidity": {
        "value": 84.8
      },
      "dewPoint": {
        "value": 2.4
      },
      "start": "2025-12-21T19:00:00+01:00",
      "end": "2025-12-22T01:00:00+01:00",
      "nominalStart": "2025-12-21T18:00:00+01:00",
      "nominalEnd": "2025-12-22T00:00:00+01:00"
    },
    {
      "symbol": {
        "n": 4,
        "clouds": 3,
        "precip": 0,
        "sunup": false
      },
      "symbolCode": {
        "next6Hours": "cloudy",
        "next12Hours": "cloudy"
      },
      "precipitation": {
        "value": 0
      },
      "temperature": {
        "value": 4.3,
        "min": 3.9,
        "max": 4.6
      },
      "wind": {
        "direction": 14,
        "speed": 1.4
      },
      "feelsLike": {
        "value": 3
      },
      "pressure": {
        "value": 1006
      },
      "cloudCover": {
        "value": 98,
        "high": 97,
        "middle": 41,
        "low": 1,
        "fog": 0
      },
      "humidity": {
        "value": 90.4
      },
      "dewPoint": {
        "value": 2.7
      },
      "start": "2025-12-22T01:00:00+01:00",
      "end": "2025-12-22T07:00:00+01:00",
      "nominalStart": "2025-12-22T00:00:00+01:00",
      "nominalEnd": "2025-12-22T06:00:00+01:00"
    },
    {
      "symbol": {
        "n": 4,
        "clouds": 3,
        "precip": 0,
        "sunup": false
      },
      "symbolCode": {
        "next6Hours": "cloudy",
        "next12Hours": "cloudy"
      },
      "precipitation": {
        "value": 0
      },
      "temperature": {
        "value": 4.1,
        "min": 3.7,
        "max": 7.6
      },
      "wind": {
        "direction": 359,
        "speed": 0.6
      },
      "feelsLike": {
        "value": 4.1
      },
      "pressure": {
        "value": 1004
      },
      "cloudCover": {
        "value": 100,
        "high": 99,
        "middle": 97,
        "low": 1,
        "fog": 0
      },
      "humidity": {
        "value": 85.6
      },
      "dewPoint": {
        "value": 1.8
      },
      "start": "2025-12-22T07:00:00+01:00",
      "end": "2025-12-22T13:00:00+01:00",
      "nominalStart": "2025-12-22T06:00:00+01:00",
      "nominalEnd": "2025-12-22T12:00:00+01:00"
    },
    {
      "symbol": {
        "n": 4,
        "clouds": 3,
        "precip": 0,
        "sunup": false
      },
      "symbolCode": {
        "next6Hours": "cloudy",
        "next12Hours": "cloudy"
      },
      "precipitation": {
        "value": 0
      },
      "temperature": {
        "value": 7.6,
        "min": 3.3,
        "max": 7.8
      },
      "wind": {
        "direction": 26,
        "speed": 1.3
      },
      "feelsLike": {
        "value": 7.6
      },
      "pressure": {
        "value": 1001
      },
      "cloudCover": {
        "value": 99,
        "high": 99,
        "middle": 33,
        "low": 2,
        "fog": 0
      },
      "humidity": {
        "value": 78.5
      },
      "dewPoint": {
        "value": 4
      },
      "start": "2025-12-22T13:00:00+01:00",
      "end": "2025-12-22T19:00:00+01:00",
      "nominalStart": "2025-12-22T12:00:00+01:00",
      "nominalEnd": "2025-12-22T18:00:00+01:00"
    },
    {
      "symbol": {
        "n": 4,
        "clouds": 3,
        "precip": 0,
        "sunup": false
      },
      "symbolCode": {
        "next6Hours": "cloudy",
        "next12Hours": "cloudy"
      },
      "precipitation": {
        "value": 0
      },
      "temperature": {
        "value": 3.3,
        "min": 1.1,
        "max": 3.3
      },
      "wind": {
        "direction": 221,
        "speed": 0.5
      },
      "feelsLike": {
        "value": 3.3
      },
      "pressure": {
        "value": 1003
      },
      "cloudCover": {
        "value": 96,
        "high": 95,
        "middle": 38,
        "low": 0,
        "fog": 0
      },
      "humidity": {
        "value": 88.5
      },
      "dewPoint": {
        "value": 1.4
      },
      "start": "2025-12-22T19:00:00+01:00",
      "end": "2025-12-23T01:00:00+01:00",
      "nominalStart": "2025-12-22T18:00:00+01:00",
      "nominalEnd": "2025-12-23T00:00:00+01:00"
    },
    {
      "symbol": {
        "n": 4,
        "clouds": 3,
        "precip": 0,
        "sunup": false
      },
      "symbolCode": {
        "next6Hours": "cloudy",
        "next12Hours": "cloudy"
      },
      "precipitation": {
        "value": 0
      },
      "temperature": {
        "value": 1.3,
        "min": 1.1,
        "max": 2.1
      },
      "wind": {
        "direction": 254,
        "speed": 1
      },
      "feelsLike": {
        "value": 1.3
      },
      "pressure": {
        "value": 1006
      },
      "cloudCover": {
        "value": 100,
        "high": 100,
        "middle": 87,
        "low": 51,
        "fog": 0
      },
      "humidity": {
        "value": 95.2
      },
      "dewPoint": {
        "value": 0.4
      },
      "start": "2025-12-23T01:00:00+01:00",
      "end": "2025-12-23T07:00:00+01:00",
      "nominalStart": "2025-12-23T00:00:00+01:00",
      "nominalEnd": "2025-12-23T06:00:00+01:00"
    },
    {
      "symbol": {
        "n": 3,
        "clouds": 2,
        "precip": 0,
        "var": "Sun",
        "sunup": false
      },
      "symbolCode": {
        "next6Hours": "partlycloudy_day",
        "next12Hours": "cloudy"
      },
      "precipitation": {
        "value": 0
      },
      "temperature": {
        "value": 1.4,
        "min": 1.3,
        "max": 5.8
      },
      "wind": {
        "direction": 280,
        "speed": 0.3
      },
      "feelsLike": {
        "value": 1.4
      },
      "pressure": {
        "value": 1008
      },
      "cloudCover": {
        "value": 82,
        "high": 63,
        "middle": 23,
        "low": 56,
        "fog": 0
      },
      "humidity": {
        "value": 93.1
      },
      "dewPoint": {
        "value": 0.2
      },
      "start": "2025-12-23T07:00:00+01:00",
      "end": "2025-12-23T13:00:00+01:00",
      "nominalStart": "2025-12-23T06:00:00+01:00",
      "nominalEnd": "2025-12-23T12:00:00+01:00"
    },
    {
      "symbol": {
        "n": 4,
        "clouds": 3,
        "precip": 0,
        "sunup": false
      },
      "symbolCode": {
        "next6Hours": "cloudy",
        "next12Hours": "cloudy"
      },
      "precipitation": {
        "value": 0
      },
      "temperature": {
        "value": 5.8,
        "min": 2.9,
        "max": 6.7
      },
      "wind": {
        "direction": 39,
        "speed": 0.6
      },
      "feelsLike": {
        "value": 5.8
      },
      "pressure": {
        "value": 1009
      },
      "cloudCover": {
        "value": 91,
        "high": 73,
        "middle": 0,
        "low": 66,
        "fog": 0
      },
      "humidity": {
        "value": 89.7
      },
      "dewPoint": {
        "value": 4.1
      },
      "start": "2025-12-23T13:00:00+01:00",
      "end": "2025-12-23T19:00:00+01:00",
      "nominalStart": "2025-12-23T12:00:00+01:00",
      "nominalEnd": "2025-12-23T18:00:00+01:00"
    },
    {
      "symbol": {
        "n": 4,
        "clouds": 3,
        "precip": 0,
        "sunup": false
      },
      "symbolCode": {
        "next6Hours": "cloudy",
        "next12Hours": "cloudy"
      },
      "precipitation": {
        "value": 0
      },
      "temperature": {
        "value": 2.9,
        "min": 1.8,
        "max": 2.9
      },
      "wind": {
        "direction": 355,
        "speed": 0.6
      },
      "feelsLike": {
        "value": 2.9
      },
      "pressure": {
        "value": 1010
      },
      "cloudCover": {
        "value": 88,
        "high": 82,
        "middle": 0,
        "low": 38,
        "fog": 0
      },
      "humidity": {
        "value": 97.2
      },
      "dewPoint": {
        "value": 2.4
      },
      "start": "2025-12-23T19:00:00+01:00",
      "end": "2025-12-24T01:00:00+01:00",
      "nominalStart": "2025-12-23T18:00:00+01:00",
      "nominalEnd": "2025-12-24T00:00:00+01:00"
    },
    {
      "symbol": {
        "n": 4,
        "clouds": 3,
        "precip": 0,
        "sunup": false
      },
      "symbolCode": {
        "next6Hours": "cloudy",
        "next12Hours": "cloudy"
      },
      "precipitation": {
        "value": 0
      },
      "temperature": {
        "value": 2.2,
        "min": 1.1,
        "max": 2.4
      },
      "wind": {
        "direction": 28,
        "speed": 1.1
      },
      "feelsLike": {
        "value": 2.2
      },
      "pressure": {
        "value": 1012
      },
      "cloudCover": {
        "value": 94,
        "high": 1,
        "middle": 0,
        "low": 94,
        "fog": 0
      },
      "humidity": {
        "value": 97.5
      },
      "dewPoint": {
        "value": 1.7
      },
      "start": "2025-12-24T01:00:00+01:00",
      "end": "2025-12-24T07:00:00+01:00",
      "nominalStart": "2025-12-24T00:00:00+01:00",
      "nominalEnd": "2025-12-24T06:00:00+01:00"
    },
    {
      "symbol": {
        "n": 4,
        "clouds": 3,
        "precip": 0,
        "sunup": false
      },
      "symbolCode": {
        "next6Hours": "cloudy",
        "next12Hours": "cloudy"
      },
      "precipitation": {
        "value": 0
      },
      "temperature": {
        "value": 1.4,
        "min": 1.3,
        "max": 4.8
      },
      "wind": {
        "direction": 18,
        "speed": 1.3
      },
      "feelsLike": {
        "value": 1.4
      },
      "pressure": {
        "value": 1013
      },
      "cloudCover": {
        "value": 100,
        "high": 96,
        "middle": 0,
        "low": 98,
        "fog": 0
      },
      "humidity": {
        "value": 97.3
      },
      "dewPoint": {
        "value": 0.9
      },
      "start": "2025-12-24T07:00:00+01:00",
      "end": "2025-12-24T13:00:00+01:00",
      "nominalStart": "2025-12-24T06:00:00+01:00",
      "nominalEnd": "2025-12-24T12:00:00+01:00"
    },
    {
      "symbol": {
        "n": 4,
        "clouds": 3,
        "precip": 0,
        "sunup": false
      },
      "symbolCode": {
        "next6Hours": "cloudy",
        "next12Hours": "cloudy"
      },
      "precipitation": {
        "value": 0
      },
      "temperature": {
        "value": 4.8,
        "min": 2.2,
        "max": 5.3
      },
      "wind": {
        "direction": 34,
        "speed": 2.3
      },
      "feelsLike": {
        "value": 3
      },
      "pressure": {
        "value": 1013
      },
      "cloudCover": {
        "value": 93,
        "high": 63,
        "middle": 0,
        "low": 81,
        "fog": 0
      },
      "humidity": {
        "value": 86.1
      },
      "dewPoint": {
        "value": 2.5
      },
      "start": "2025-12-24T13:00:00+01:00",
      "end": "2025-12-24T19:00:00+01:00",
      "nominalStart": "2025-12-24T12:00:00+01:00",
      "nominalEnd": "2025-12-24T18:00:00+01:00"
    },
    {
      "symbol": {
        "n": 4,
        "clouds": 3,
        "precip": 0,
        "sunup": false
      },
      "symbolCode": {
        "next6Hours": "cloudy",
        "next12Hours": "cloudy"
      },
      "precipitation": {
        "value": 0
      },
      "temperature": {
        "value": 2.2,
        "min": 1.9,
        "max": 2.3
      },
      "wind": {
        "direction": 35,
        "speed": 3.4
      },
      "feelsLike": {
        "value": -1
      },
      "pressure": {
        "value": 1015
      },
      "cloudCover": {
        "value": 97,
        "high": 8,
        "middle": 0,
        "low": 96,
        "fog": 0
      },
      "humidity": {
        "value": 94.1
      },
      "dewPoint": {
        "value": 1.2
      },
      "start": "2025-12-24T19:00:00+01:00",
      "end": "2025-12-25T01:00:00+01:00",
      "nominalStart": "2025-12-24T18:00:00+01:00",
      "nominalEnd": "2025-12-25T00:00:00+01:00"
    },
    {
      "symbol": {
        "n": 4,
        "clouds": 3,
        "precip": 0,
        "sunup": false
      },
      "symbolCode": {
        "next6Hours": "cloudy",
        "next12Hours": "cloudy"
      },
      "precipitation": {
        "value": 0
      },
      "temperature": {
        "value": 1.9,
        "min": 0.7,
        "max": 2
      },
      "wind": {
        "direction": 39,
        "speed": 3.3
      },
      "feelsLike": {
        "value": -1
      },
      "pressure": {
        "value": 1015
      },
      "cloudCover": {
        "value": 100,
        "high": 0,
        "middle": 0,
        "low": 100,
        "fog": 0
      },
      "humidity": {
        "value": 93.9
      },
      "dewPoint": {
        "value": 0.9
      },
      "start": "2025-12-25T01:00:00+01:00",
      "end": "2025-12-25T07:00:00+01:00",
      "nominalStart": "2025-12-25T00:00:00+01:00",
      "nominalEnd": "2025-12-25T06:00:00+01:00"
    },
    {
      "symbol": {
        "n": 4,
        "clouds": 3,
        "precip": 0,
        "sunup": false
      },
      "symbolCode": {
        "next6Hours": "cloudy",
        "next12Hours": "partlycloudy_day"
      },
      "precipitation": {
        "value": 0
      },
      "temperature": {
        "value": 0.7,
        "min": -0.1,
        "max": 0.9
      },
      "wind": {
        "direction": 39,
        "speed": 4.3
      },
      "feelsLike": {
        "value": -4
      },
      "pressure": {
        "value": 1015
      },
      "cloudCover": {
        "value": 100,
        "high": 0,
        "middle": 0,
        "low": 100,
        "fog": 0
      },
      "humidity": {
        "value": 87.2
      },
      "dewPoint": {
        "value": -1.4
      },
      "start": "2025-12-25T07:00:00+01:00",
      "end": "2025-12-25T13:00:00+01:00",
      "nominalStart": "2025-12-25T06:00:00+01:00",
      "nominalEnd": "2025-12-25T12:00:00+01:00"
    },
    {
      "symbol": {
        "n": 4,
        "clouds": 3,
        "precip": 0,
        "sunup": false
      },
      "symbolCode": {
        "next6Hours": "cloudy",
        "next12Hours": "partlycloudy_day"
      },
      "precipitation": {
        "value": 0
      },
      "temperature": {
        "value": 0.9,
        "min": -0.5,
        "max": 1.2
      },
      "wind": {
        "direction": 42,
        "speed": 4.9
      },
      "feelsLike": {
        "value": -4
      },
      "pressure": {
        "value": 1015
      },
      "cloudCover": {
        "value": 87,
        "high": 0,
        "middle": 0,
        "low": 87,
        "fog": 0
      },
      "humidity": {
        "value": 75.2
      },
      "dewPoint": {
        "value": -3.2
      },
      "start": "2025-12-25T13:00:00+01:00",
      "end": "2025-12-25T19:00:00+01:00",
      "nominalStart": "2025-12-25T12:00:00+01:00",
      "nominalEnd": "2025-12-25T18:00:00+01:00"
    },
    {
      "symbol": {
        "n": 2,
        "clouds": 1,
        "precip": 0,
        "var": "Moon",
        "sunup": false
      },
      "symbolCode": {
        "next6Hours": "fair_night",
        "next12Hours": "partlycloudy_night"
      },
      "precipitation": {
        "value": 0
      },
      "temperature": {
        "value": -0.5,
        "min": -1.5,
        "max": -0.5
      },
      "wind": {
        "direction": 36,
        "speed": 4.5
      },
      "feelsLike": {
        "value": -5
      },
      "pressure": {
        "value": 1016
      },
      "cloudCover": {
        "value": 32,
        "high": 0,
        "middle": 13,
        "low": 29,
        "fog": 0
      },
      "humidity": {
        "value": 74.5
      },
      "dewPoint": {
        "value": -4.7
      },
      "start": "2025-12-25T19:00:00+01:00",
      "end": "2025-12-26T01:00:00+01:00",
      "nominalStart": "2025-12-25T18:00:00+01:00",
      "nominalEnd": "2025-12-26T00:00:00+01:00"
    },
    {
      "symbol": {
        "n": 3,
        "clouds": 2,
        "precip": 0,
        "var": "Moon",
        "sunup": false
      },
      "symbolCode": {
        "next6Hours": "partlycloudy_night",
        "next12Hours": "cloudy"
      },
      "precipitation": {
        "value": 0
      },
      "temperature": {
        "value": -1.4,
        "min": -1.9,
        "max": -1.2
      },
      "wind": {
        "direction": 42,
        "speed": 4.6
      },
      "feelsLike": {
        "value": -6
      },
      "pressure": {
        "value": 1016
      },
      "cloudCover": {
        "value": 66,
        "high": 0,
        "middle": 42,
        "low": 59,
        "fog": 0
      },
      "humidity": {
        "value": 73.5
      },
      "dewPoint": {
        "value": -5.8
      },
      "start": "2025-12-26T01:00:00+01:00",
      "end": "2025-12-26T07:00:00+01:00",
      "nominalStart": "2025-12-26T00:00:00+01:00",
      "nominalEnd": "2025-12-26T06:00:00+01:00"
    },
    {
      "symbol": {
        "n": 4,
        "clouds": 3,
        "precip": 0,
        "sunup": false
      },
      "symbolCode": {
        "next6Hours": "cloudy",
        "next12Hours": "lightsnow"
      },
      "precipitation": {
        "value": 0.3
      },
      "temperature": {
        "value": -1.9,
        "min": -2.2,
        "max": -1
      },
      "wind": {
        "direction": 44,
        "speed": 4.1
      },
      "feelsLike": {
        "value": -7
      },
      "pressure": {
        "value": 1016
      },
      "cloudCover": {
        "value": 97,
        "high": 0,
        "middle": 95,
        "low": 73,
        "fog": 0
      },
      "humidity": {
        "value": 74.6
      },
      "dewPoint": {
        "value": -6.1
      },
      "start": "2025-12-26T07:00:00+01:00",
      "end": "2025-12-26T13:00:00+01:00",
      "nominalStart": "2025-12-26T06:00:00+01:00",
      "nominalEnd": "2025-12-26T12:00:00+01:00"
    },
    {
      "symbol": {
        "n": 49,
        "clouds": 3,
        "precipPhase": "Snow",
        "precip": 1,
        "sunup": false
      },
      "symbolCode": {
        "next6Hours": "lightsnow",
        "next12Hours": "lightsnowshowers_day"
      },
      "precipitation": {
        "value": 0.8
      },
      "temperature": {
        "value": -1,
        "min": -1.1,
        "max": -0.5
      },
      "wind": {
        "direction": 51,
        "speed": 2.6
      },
      "feelsLike": {
        "value": -4
      },
      "pressure": {
        "value": 1016
      },
      "cloudCover": {
        "value": 98,
        "high": 0,
        "middle": 88,
        "low": 96,
        "fog": 0
      },
      "humidity": {
        "value": 75.9
      },
      "dewPoint": {
        "value": -5
      },
      "start": "2025-12-26T13:00:00+01:00",
      "end": "2025-12-26T19:00:00+01:00",
      "nominalStart": "2025-12-26T12:00:00+01:00",
      "nominalEnd": "2025-12-26T18:00:00+01:00"
    },
    {
      "symbol": {
        "n": 4,
        "clouds": 3,
        "precip": 0,
        "sunup": false
      },
      "symbolCode": {
        "next6Hours": "cloudy",
        "next12Hours": "partlycloudy_night"
      },
      "precipitation": {
        "value": 0
      },
      "temperature": {
        "value": -0.9,
        "min": -2,
        "max": -0.2
      },
      "wind": {
        "direction": 54,
        "speed": 1.4
      },
      "feelsLike": {
        "value": -3
      },
      "pressure": {
        "value": 1018
      },
      "cloudCover": {
        "value": 100,
        "high": 0,
        "middle": 100,
        "low": 56,
        "fog": 0
      },
      "humidity": {
        "value": 85.2
      },
      "dewPoint": {
        "value": -3.3
      },
      "start": "2025-12-26T19:00:00+01:00",
      "end": "2025-12-27T01:00:00+01:00",
      "nominalStart": "2025-12-26T18:00:00+01:00",
      "nominalEnd": "2025-12-27T00:00:00+01:00"
    },
    {
      "symbol": {
        "n": 3,
        "clouds": 2,
        "precip": 0,
        "var": "Moon",
        "sunup": false
      },
      "symbolCode": {
        "next6Hours": "partlycloudy_night",
        "next12Hours": "partlycloudy_day"
      },
      "precipitation": {
        "value": 0
      },
      "temperature": {
        "value": -1.2,
        "min": -1.2,
        "max": -0.6
      },
      "wind": {
        "direction": 33,
        "speed": 1.4
      },
      "feelsLike": {
        "value": -3
      },
      "pressure": {
        "value": 1020
      },
      "cloudCover": {
        "value": 42,
        "high": 0,
        "middle": 42,
        "low": 0,
        "fog": 0
      },
      "humidity": {
        "value": 79.2
      },
      "dewPoint": {
        "value": -4.6
      },
      "start": "2025-12-27T01:00:00+01:00",
      "end": "2025-12-27T07:00:00+01:00",
      "nominalStart": "2025-12-27T00:00:00+01:00",
      "nominalEnd": "2025-12-27T06:00:00+01:00"
    },
    {
      "symbol": {
        "n": 3,
        "clouds": 2,
        "precip": 0,
        "var": "Sun",
        "sunup": false
      },
      "symbolCode": {
        "next6Hours": "partlycloudy_day"
      },
      "precipitation": {
        "value": 0
      },
      "temperature": {
        "value": -0.7,
        "min": -0.8,
        "max": 4.3
      },
      "wind": {
        "direction": 38,
        "speed": 1.6
      },
      "feelsLike": {
        "value": -3
      },
      "pressure": {
        "value": 1021
      },
      "cloudCover": {
        "value": 78,
        "high": 77,
        "middle": 0,
        "low": 1,
        "fog": 0
      },
      "humidity": {
        "value": 68.6
      },
      "dewPoint": {
        "value": -6.1
      },
      "start": "2025-12-27T07:00:00+01:00",
      "end": "2025-12-27T13:00:00+01:00",
      "nominalStart": "2025-12-27T06:00:00+01:00",
      "nominalEnd": "2025-12-27T12:00:00+01:00"
    }
  ],
  "status": {
    "code": "Ok"
  },
  "_links": {
    "self": {
      "href": "/api/v0/locations/2-2660646/forecast"
    },
    "parent": {
      "href": "/api/v0/locations/2-2660646"
    }
  }
}
