{
  "created": "2025-08-31T19:17:01+02:00",
  "update": "2025-08-31T20:17:01+02:00",
  "uv": {
    "duration": {
      "days": 2,
      "hours": 11
    },
    "url": "https://dsa.no/sol-og-solarium/slik-beskytter-du-deg-i-sola",
    "displayUrl": "dsa.no"
  },
  "dayIntervals": [
    {
      "start": "2025-08-31T20:00:00+02:00",
      "end": "2025-08-31T23:00:00+02:00",
      "twentyFourHourSymbol": "rain",
      "twelveHourSymbols": [
        null,
        "rain"
      ],
      "sixHourSymbols": [
        null,
        null,
        null,
        "rain"
      ],
      "symbolConfidence": "None",
      "precipitation": {
        "value": 0
      },
      "temperature": {
        "value": 20.2,
        "min": 19.1,
        "max": 21.4
      },
      "wind": {
        "min": 0.6,
        "max": 1
      }
    },
    {
      "start": "2025-09-01T00:00:00+02:00",
      "end": "2025-09-01T23:00:00+02:00",
      "twentyFourHourSymbol": "rain",
      "twelveHourSymbols": [
        "rain",
        "heavyrainshowers_day"
      ],
      "sixHourSymbols": [
        "heavyrain",
        "rain",
        "heavyrain",
        "heavyrainshowers_night"
      ],
      "symbolConfidence": "None",
      "precipitation": {
        "value": 37.5
      },
      "temperature": {
        "value": 20.9,
        "min": 14.3,
        "max": 20.9
      },
      "wind": {
        "min": 1.5,
        "max": 2
      }
    },
    {
      "start": "2025-09-02T00:00:00+02:00",
      "end": "2025-09-02T23:00:00+02:00",
      "twentyFourHourSymbol": "partlycloudy_day",
      "twelveHourSymbols": [
        "partlycloudy_day",
        "lightrainshowers_day"
      ],
      "sixHourSymbols": [
        "partlycloudy_night",
        "fair_day",
        "partlycloudy_day",
        "rain"
      ],
      "symbolConfidence": "None",
      "precipitation": {
        "value": 1.8
      },
      "temperature": {
        "value": 19.5,
        "min": 13,
        "max": 20
      },
      "wind": {
        "min": 1.5,
        "max": 4.1
      }
    },
    {
      "start": "2025-09-03T00:00:00+02:00",
      "end": "2025-09-03T23:00:00+02:00",
      "twentyFourHourSymbol": "partlycloudy_day",
      "twelveHourSymbols": [
        "partlycloudy_day",
        "fair_day"
      ],
      "sixHourSymbols": [
        "partlycloudy_night",
        "partlycloudy_day",
        "fair_day",
        "fair_night"
      ],
      "symbolConfidence": "None",
      "precipitation": {
        "value": 0.1
      },
      "temperature": {
        "value": 21.3,
        "min": 14.1,
        "max": 22.3
      },
      "wind": {
        "min": 1.5,
        "max": 2.8
      }
    },
    {
      "start": "2025-09-04T00:00:00+02:00",
      "end": "2025-09-04T23:00:00+02:00",
      "twentyFourHourSymbol": "rainshowers_day",
      "twelveHourSymbols": [
        "rainshowers_day",
        "lightrainshowers_day"
      ],
      "sixHourSymbols": [
        "clearsky_night",
        "heavyrainshowers_day",
        "rain",
        "fair_night"
      ],
      "symbolConfidence": "None",
      "precipitation": {
        "value": 8.7
      },
      "temperature": {
        "value": 17.9,
        "min": 13.2,
        "max": 19.9
      },
      "wind": {
        "min": 0.4,
        "max": 1.4
      }
    },
    {
      "start": "2025-09-05T00:00:00+02:00",
      "end": "2025-09-05T23:00:00+02:00",
      "twentyFourHourSymbol": "fair_day",
      "twelveHourSymbols": [
        "partlycloudy_day",
        "clearsky_day"
      ],
      "sixHourSymbols": [
        "partlycloudy_night",
        "partlycloudy_day",
        "clearsky_day",
        "clearsky_night"
      ],
      "symbolConfidence": "None",
      "precipitation": {
        "value": 0.2
      },
      "temperature": {
        "value": 19.8,
        "min": 12.4,
        "max": 20.1
      },
      "wind": {
        "min": 0.4,
        "max": 3
      }
    },
    {
      "start": "2025-09-06T00:00:00+02:00",
      "end": "2025-09-06T23:00:00+02:00",
      "twentyFourHourSymbol": "clearsky_day",
      "twelveHourSymbols": [
        "clearsky_day",
        "clearsky_day"
      ],
      "sixHourSymbols": [
        "clearsky_night",
        "fair_day",
        "clearsky_day",
        "clearsky_night"
      ],
      "symbolConfidence": "None",
      "precipitation": {
        "value": 0
      },
      "temperature": {
        "value": 22.3,
        "min": 12.5,
        "max": 23.5
      },
      "wind": {
        "min": 0.5,
        "max": 1.5
      }
    },
    {
      "start": "2025-09-07T00:00:00+02:00",
      "end": "2025-09-07T23:00:00+02:00",
      "twentyFourHourSymbol": "fair_day",
      "twelveHourSymbols": [
        "fair_day",
        "clearsky_day"
      ],
      "sixHourSymbols": [
        "fair_night",
        "partlycloudy_day",
        "clearsky_day",
        "clearsky_night"
      ],
      "symbolConfidence": "None",
      "precipitation": {
        "value": 0
      },
      "temperature": {
        "value": 24.6,
        "min": 15,
        "max": 25.6
      },
      "wind": {
        "min": 0.1,
        "max": 0.9
      }
    },
    {
      "start": "2025-09-08T00:00:00+02:00",
      "end": "2025-09-08T23:00:00+02:00",
      "twentyFourHourSymbol": "clearsky_day",
      "twelveHourSymbols": [
        "clearsky_day",
        "clearsky_day"
      ],
      "sixHourSymbols": [
        "clearsky_night",
        "clearsky_day",
        "clearsky_day",
        "clearsky_night"
      ],
      "symbolConfidence": "None",
      "precipitation": {
        "value": 0
      },
      "temperature": {
        "value": 23.5,
        "min": 15.2,
        "max": 23.9
      },
      "wind": {
        "min": 0.4,
        "max": 2.5
      }
    },
    {
      "start": "2025-09-09T00:00:00+02:00",
      "end": "2025-09-09T23:00:00+02:00",
      "twentyFourHourSymbol": "fair_day",
      "twelveHourSymbols": [
        "fair_day",
        "fair_day"
      ],
      "sixHourSymbols": [
        "clearsky_night",
        "fair_day",
        "fair_day",
        "clearsky_night"
      ],
      "symbolConfidence": "None",
      "precipitation": {
        "value": 0
      },
      "temperature": {
        "value": 23.7,
        "min": 14.7,
        "max": 24.7
      },
      "wind": {
        "min": 0.4,
        "max": 0.8
      }
    }
  ],
  "shortIntervals": [
    {
      "symbol": {
        "n": 4,
        "clouds": 3,
        "precip": 0,
        "sunup": false
      },
      "symbolCode": {
        "next1Hour": "cloudy",
        "next6Hours": "heavyrain",
        "next12Hours": "heavyrain"
      },
      "precipitation": {
        "value": 0
      },
      "temperature": {
        "value": 20.4
      },
      "wind": {
        "direction": 126,
        "speed": 0.6
      },
      "feelsLike": {
        "value": 20.4
      },
      "pressure": {
        "value": 1010
      },
      "uvIndex": {
        "value": 0
      },
      "cloudCover": {
        "value": 99,
        "high": 98,
        "middle": 53,
        "low": 0,
        "fog": 0
      },
      "humidity": {
        "value": 72.7
      },
      "dewPoint": {
        "value": 15.5
      },
      "start": "2025-08-31T21:00:00+02:00",
      "end": "2025-08-31T22:00:00+02:00"
    },
    {
      "symbol": {
        "n": 4,
        "clouds": 3,
        "precip": 0,
        "sunup": false
      },
      "symbolCode": {
        "next1Hour": "cloudy",
        "next6Hours": "heavyrain",
        "next12Hours": "heavyrain"
      },
      "precipitation": {
        "value": 0
      },
      "temperature": {
        "value": 20.2
      },
      "wind": {
        "direction": 179,
        "speed": 0.8
      },
      "feelsLike": {
        "value": 20.2
      },
      "pressure": {
        "value": 1010
      },
      "uvIndex": {
        "value": 0
      },
      "cloudCover": {
        "value": 88,
        "high": 83,
        "middle": 34,
        "low": 0,
        "fog": 0
      },
      "humidity": {
        "value": 74.8
      },
      "dewPoint": {
        "value": 15.7
      },
      "start": "2025-08-31T22:00:00+02:00",
      "end": "2025-08-31T23:00:00+02:00"
    },
    {
      "symbol": {
        "n": 3,
        "clouds": 2,
        "precip": 0,
        "var": "Moon",
        "sunup": false
      },
      "symbolCode": {
        "next1Hour": "partlycloudy_night",
        "next6Hours": "heavyrain",
        "next12Hours": "heavyrain"
      },
      "precipitation": {
        "value": 0
      },
      "temperature": {
        "value": 19.1
      },
      "wind": {
        "direction": 211,
        "speed": 1
      },
      "feelsLike": {
        "value": 19.1
      },
      "pressure": {
        "value": 1010
      },
      "uvIndex": {
        "value": 0
      },
      "cloudCover": {
        "value": 99,
        "high": 99,
        "middle": 8,
        "low": 0,
        "fog": 0
      },
      "humidity": {
        "value": 77.6
      },
      "dewPoint": {
        "value": 15.2
      },
      "start": "2025-08-31T23:00:00+02:00",
      "end": "2025-09-01T00:00:00+02:00"
    },
    {
      "symbol": {
        "n": 4,
        "clouds": 3,
        "precip": 0,
        "sunup": false
      },
      "symbolCode": {
        "next1Hour": "cloudy",
        "next6Hours": "heavyrain",
        "next12Hours": "rain"
      },
      "precipitation": {
        "value": 0
      },
      "temperature": {
        "value": 18.8
      },
      "wind": {
        "direction": 212,
        "speed": 1.6
      },
      "feelsLike": {
        "value": 18.8
      },
      "pressure": {
        "value": 1010
      },
      "uvIndex": {
        "value": 0
      },
      "cloudCover": {
        "value": 99,
        "high": 98,
        "middle": 73,
        "low": 1,
        "fog": 0
      },
      "humidity": {
        "value": 78.2
      },
      "dewPoint": {
        "value": 15.1
      },
      "start": "2025-09-01T00:00:00+02:00",
      "end": "2025-09-01T01:00:00+02:00"
    },
    {
      "symbol": {
        "n": 10,
        "clouds": 3,
        "precipPhase": "Rain",
        "precip": 3,
        "sunup": false
      },
      "symbolCode": {
        "next1Hour": "heavyrain",
        "next6Hours": "heavyrain",
        "next12Hours": "rain"
      },
      "precipitation": {
        "value": 2.5
      },
      "temperature": {
        "value": 18.6
      },
      "wind": {
        "direction": 215,
        "speed": 2.6
      },
      "feelsLike": {
        "value": 18.6
      },
      "pressure": {
        "value": 1009
      },
      "uvIndex": {
        "value": 0
      },
      "cloudCover": {
        "value": 100,
        "high": 100,
        "middle": 78,
        "low": 1,
        "fog": 0
      },
      "humidity": {
        "value": 78.5
      },
      "dewPoint": {
        "value": 14.9
      },
      "start": "2025-09-01T01:00:00+02:00",
      "end": "2025-09-01T02:00:00+02:00"
    },
    {
      "symbol": {
        "n": 10,
        "clouds": 3,
        "precipPhase": "Rain",
        "precip": 3,
        "sunup": false
      },
      "symbolCode": {
        "next1Hour": "heavyrain",
        "next6Hours": "heavyrain",
        "next12Hours": "rain"
      },
      "precipitation": {
        "value": 3
      },
      "temperature": {
        "value": 17.5
      },
      "wind": {
        "direction": 208,
        "speed": 1.4
      },
      "feelsLike": {
        "value": 17.5
      },
      "pressure": {
        "value": 1009
      },
      "uvIndex": {
        "value": 0
      },
      "cloudCover": {
        "value": 100,
        "high": 100,
        "middle": 99,
        "low": 2,
        "fog": 0
      },
      "humidity": {
        "value": 86.9
      },
      "dewPoint": {
        "value": 15.4
      },
      "start": "2025-09-01T02:00:00+02:00",
      "end": "2025-09-01T03:00:00+02:00"
    },
    {
      "symbol": {
        "n": 10,
        "clouds": 3,
        "precipPhase": "Rain",
        "precip": 3,
        "sunup": false
      },
      "symbolCode": {
        "next1Hour": "heavyrain",
        "next6Hours": "heavyrain",
        "next12Hours": "rain"
      },
      "precipitation": {
        "value": 2.9
      },
      "temperature": {
        "value": 17.1
      },
      "wind": {
        "direction": 215,
        "speed": 1.4
      },
      "feelsLike": {
        "value": 17.1
      },
      "pressure": {
        "value": 1009
      },
      "uvIndex": {
        "value": 0
      },
      "cloudCover": {
        "value": 100,
        "high": 100,
        "middle": 99,
        "low": 15,
        "fog": 0
      },
      "humidity": {
        "value": 90.5
      },
      "dewPoint": {
        "value": 15.7
      },
      "start": "2025-09-01T03:00:00+02:00",
      "end": "2025-09-01T04:00:00+02:00"
    },
    {
      "symbol": {
        "n": 10,
        "clouds": 3,
        "precipPhase": "Rain",
        "precip": 3,
        "sunup": false
      },
      "symbolCode": {
        "next1Hour": "heavyrain",
        "next6Hours": "heavyrain",
        "next12Hours": "rain"
      },
      "precipitation": {
        "value": 3.4
      },
      "temperature": {
        "value": 16.9
      },
      "wind": {
        "direction": 236,
        "speed": 1.3
      },
      "feelsLike": {
        "value": 16.9
      },
      "pressure": {
        "value": 1009
      },
      "uvIndex": {
        "value": 0
      },
      "cloudCover": {
        "value": 100,
        "high": 100,
        "middle": 100,
        "low": 6,
        "fog": 0
      },
      "humidity": {
        "value": 91.9
      },
      "dewPoint": {
        "value": 15.7
      },
      "start": "2025-09-01T04:00:00+02:00",
      "end": "2025-09-01T05:00:00+02:00"
    },
    {
      "symbol": {
        "n": 10,
        "clouds": 3,
        "precipPhase": "Rain",
        "precip": 3,
        "sunup": false
      },
      "symbolCode": {
        "next1Hour": "heavyrain",
        "next6Hours": "heavyrain",
        "next12Hours": "heavyrain"
      },
      "precipitation": {
        "value": 4
      },
      "temperature": {
        "value": 16.8
      },
      "wind": {
        "direction": 215,
        "speed": 1.5
      },
      "feelsLike": {
        "value": 16.8
      },
      "pressure": {
        "value": 1010
      },
      "uvIndex": {
        "value": 0
      },
      "cloudCover": {
        "value": 100,
        "high": 100,
        "middle": 100,
        "low": 35,
        "fog": 0
      },
      "humidity": {
        "value": 92.4
      },
      "dewPoint": {
        "value": 15.7
      },
      "start": "2025-09-01T05:00:00+02:00",
      "end": "2025-09-01T06:00:00+02:00"
    },
    {
      "symbol": {
        "n": 9,
        "clouds": 3,
        "precipPhase": "Rain",
        "precip": 2,
        "sunup": false
      },
      "symbolCode": {
        "next1Hour": "rain",
        "next6Hours": "rain",
        "next12Hours": "rain"
      },
      "precipitation": {
        "value": 0.4
      },
      "temperature": {
        "value": 16.6
      },
      "wind": {
        "direction": 183,
        "speed": 1.9
      },
      "feelsLike": {
        "value": 16.6
      },
      "pressure": {
        "value": 1010
      },
      "uvIndex": {
        "value": 0
      },
      "cloudCover": {
        "value": 100,
        "high": 40,
        "middle": 100,
        "low": 24,
        "fog": 0
      },
      "humidity": {
        "value": 93.9
      },
      "dewPoint": {
        "value": 15.8
      },
      "start": "2025-09-01T06:00:00+02:00",
      "end": "2025-09-01T07:00:00+02:00"
    },
    {
      "symbol": {
        "n": 10,
        "clouds": 3,
        "precipPhase": "Rain",
        "precip": 3,
        "sunup": false
      },
      "symbolCode": {
        "next1Hour": "heavyrain",
        "next6Hours": "rain",
        "next12Hours": "rain"
      },
      "precipitation": {
        "value": 1
      },
      "temperature": {
        "value": 16.4
      },
      "wind": {
        "direction": 225,
        "speed": 1.9
      },
      "feelsLike": {
        "value": 16.4
      },
      "pressure": {
        "value": 1010
      },
      "uvIndex": {
        "value": 0
      },
      "cloudCover": {
        "value": 100,
        "high": 91,
        "middle": 100,
        "low": 27,
        "fog": 0
      },
      "humidity": {
        "value": 94.4
      },
      "dewPoint": {
        "value": 15.6
      },
      "start": "2025-09-01T07:00:00+02:00",
      "end": "2025-09-01T08:00:00+02:00"
    },
    {
      "symbol": {
        "n": 9,
        "clouds": 3,
        "precipPhase": "Rain",
        "precip": 2,
        "sunup": false
      },
      "symbolCode": {
        "next1Hour": "rain",
        "next6Hours": "rain",
        "next12Hours": "rain"
      },
      "precipitation": {
        "value": 0.7
      },
      "temperature": {
        "value": 16.7
      },
      "wind": {
        "direction": 243,
        "speed": 1.6
      },
      "feelsLike": {
        "value": 16.7
      },
      "pressure": {
        "value": 1011
      },
      "uvIndex": {
        "value": 0.3
      },
      "cloudCover": {
        "value": 99,
        "high": 77,
        "middle": 95,
        "low": 4,
        "fog": 0
      },
      "humidity": {
        "value": 94.4
      },
      "dewPoint": {
        "value": 16
      },
      "start": "2025-09-01T08:00:00+02:00",
      "end": "2025-09-01T09:00:00+02:00"
    },
    {
      "symbol": {
        "n": 9,
        "clouds": 3,
        "precipPhase": "Rain",
        "precip": 2,
        "sunup": false
      },
      "symbolCode": {
        "next1Hour": "rain",
        "next6Hours": "rain",
        "next12Hours": "rain"
      },
      "precipitation": {
        "value": 0.4
      },
      "temperature": {
        "value": 17
      },
      "wind": {
        "direction": 220,
        "speed": 2
      },
      "feelsLike": {
        "value": 17
      },
      "pressure": {
        "value": 1011
      },
      "uvIndex": {
        "value": 1
      },
      "cloudCover": {
        "value": 100,
        "high": 13,
        "middle": 100,
        "low": 27,
        "fog": 0
      },
      "humidity": {
        "value": 93.3
      },
      "dewPoint": {
        "value": 16.1
      },
      "start": "2025-09-01T09:00:00+02:00",
      "end": "2025-09-01T10:00:00+02:00"
    },
    {
      "symbol": {
        "n": 4,
        "clouds": 3,
        "precip": 0,
        "sunup": false
      },
      "symbolCode": {
        "next1Hour": "cloudy",
        "next6Hours": "rain",
        "next12Hours": "rainshowers_day"
      },
      "precipitation": {
        "value": 0
      },
      "temperature": {
        "value": 17.4
      },
      "wind": {
        "direction": 238,
        "speed": 2.7
      },
      "feelsLike": {
        "value": 17.4
      },
      "pressure": {
        "value": 1011
      },
      "uvIndex": {
        "value": 2.4
      },
      "cloudCover": {
        "value": 97,
        "high": 59,
        "middle": 53,
        "low": 69,
        "fog": 0
      },
      "humidity": {
        "value": 89.8
      },
      "dewPoint": {
        "value": 15.9
      },
      "start": "2025-09-01T10:00:00+02:00",
      "end": "2025-09-01T11:00:00+02:00"
    },
    {
      "symbol": {
        "n": 3,
        "clouds": 2,
        "precip": 0,
        "var": "Sun",
        "sunup": false
      },
      "symbolCode": {
        "next1Hour": "partlycloudy_day",
        "next6Hours": "heavyrain",
        "next12Hours": "heavyrainshowers_day"
      },
      "precipitation": {
        "value": 0
      },
      "temperature": {
        "value": 18.1
      },
      "wind": {
        "direction": 263,
        "speed": 2
      },
      "feelsLike": {
        "value": 18.1
      },
      "pressure": {
        "value": 1011
      },
      "uvIndex": {
        "value": 4
      },
      "cloudCover": {
        "value": 79,
        "high": 60,
        "middle": 19,
        "low": 38,
        "fog": 0
      },
      "humidity": {
        "value": 83.8
      },
      "dewPoint": {
        "value": 15.5
      },
      "start": "2025-09-01T11:00:00+02:00",
      "end": "2025-09-01T12:00:00+02:00"
    },
    {
      "symbol": {
        "n": 3,
        "clouds": 2,
        "precip": 0,
        "var": "Sun",
        "sunup": false
      },
      "symbolCode": {
        "next1Hour": "partlycloudy_day",
        "next6Hours": "heavyrain",
        "next12Hours": "heavyrainshowers_day"
      },
      "precipitation": {
        "value": 0
      },
      "temperature": {
        "value": 19.2
      },
      "wind": {
        "direction": 236,
        "speed": 2
      },
      "feelsLike": {
        "value": 19.2
      },
      "pressure": {
        "value": 1011
      },
      "uvIndex": {
        "value": 5.4
      },
      "cloudCover": {
        "value": 75,
        "high": 46,
        "middle": 25,
        "low": 44,
        "fog": 0
      },
      "humidity": {
        "value": 80
      },
      "dewPoint": {
        "value": 15.8
      },
      "start": "2025-09-01T12:00:00+02:00",
      "end": "2025-09-01T13:00:00+02:00"
    },
    {
      "symbol": {
        "n": 4,
        "clouds": 3,
        "precip": 0,
        "sunup": false
      },
      "symbolCode": {
        "next1Hour": "cloudy",
        "next6Hours": "heavyrain",
        "next12Hours": "rainshowers_day"
      },
      "precipitation": {
        "value": 0
      },
      "temperature": {
        "value": 20
      },
      "wind": {
        "direction": 249,
        "speed": 2.1
      },
      "feelsLike": {
        "value": 20
      },
      "pressure": {
        "value": 1011
      },
      "uvIndex": {
        "value": 6.3
      },
      "cloudCover": {
        "value": 93,
        "high": 73,
        "middle": 48,
        "low": 66,
        "fog": 0
      },
      "humidity": {
        "value": 75.6
      },
      "dewPoint": {
        "value": 15.7
      },
      "start": "2025-09-01T13:00:00+02:00",
      "end": "2025-09-01T14:00:00+02:00"
    },
    {
      "symbol": {
        "n": 9,
        "clouds": 3,
        "precipPhase": "Rain",
        "precip": 2,
        "sunup": false
      },
      "symbolCode": {
        "next1Hour": "rain",
        "next6Hours": "heavyrain",
        "next12Hours": "lightrainshowers_day"
      },
      "precipitation": {
        "value": 0.7
      },
      "temperature": {
        "value": 20.9
      },
      "wind": {
        "direction": 262,
        "speed": 2.1
      },
      "feelsLike": {
        "value": 20.9
      },
      "pressure": {
        "value": 1010
      },
      "uvIndex": {
        "value": 6.2
      },
      "cloudCover": {
        "value": 100,
        "high": 100,
        "middle": 73,
        "low": 18,
        "fog": 0
      },
      "humidity": {
        "value": 71.1
      },
      "dewPoint": {
        "value": 15.6
      },
      "start": "2025-09-01T14:00:00+02:00",
      "end": "2025-09-01T15:00:00+02:00"
    },
    {
      "symbol": {
        "n": 10,
        "clouds": 3,
        "precipPhase": "Rain",
        "precip": 3,
        "sunup": false
      },
      "symbolCode": {
        "next1Hour": "heavyrain",
        "next6Hours": "heavyrain",
        "next12Hours": "lightrainshowers_day"
      },
      "precipitation": {
        "value": 2.2
      },
      "temperature": {
        "value": 19.2
      },
      "wind": {
        "direction": 228,
        "speed": 2.1
      },
      "feelsLike": {
        "value": 19.2
      },
      "pressure": {
        "value": 1010
      },
      "uvIndex": {
        "value": 5.3
      },
      "cloudCover": {
        "value": 100,
        "high": 99,
        "middle": 88,
        "low": 71,
        "fog": 0
      },
      "humidity": {
        "value": 75.3
      },
      "dewPoint": {
        "value": 14.9
      },
      "start": "2025-09-01T15:00:00+02:00",
      "end": "2025-09-01T16:00:00+02:00"
    },
    {
      "symbol": {
        "n": 10,
        "clouds": 3,
        "precipPhase": "Rain",
        "precip": 3,
        "sunup": false
      },
      "symbolCode": {
        "next1Hour": "heavyrain",
        "next6Hours": "heavyrainshowers_day",
        "next12Hours": "lightrainshowers_day"
      },
      "precipitation": {
        "value": 4.8
      },
      "temperature": {
        "value": 18.4
      },
      "wind": {
        "direction": 230,
        "speed": 1.7
      },
      "feelsLike": {
        "value": 18.4
      },
      "pressure": {
        "value": 1010
      },
      "uvIndex": {
        "value": 3.8
      },
      "cloudCover": {
        "value": 100,
        "high": 100,
        "middle": 99,
        "low": 18,
        "fog": 0
      },
      "humidity": {
        "value": 83.9
      },
      "dewPoint": {
        "value": 15.8
      },
      "start": "2025-09-01T16:00:00+02:00",
      "end": "2025-09-01T17:00:00+02:00"
    },
    {
      "symbol": {
        "n": 10,
        "clouds": 3,
        "precipPhase": "Rain",
        "precip": 3,
        "sunup": false
      },
      "symbolCode": {
        "next1Hour": "heavyrain",
        "next6Hours": "heavyrainshowers_day",
        "next12Hours": "lightrainshowers_day"
      },
      "precipitation": {
        "value": 5.2
      },
      "temperature": {
        "value": 17.6
      },
      "wind": {
        "direction": 193,
        "speed": 1.9
      },
      "feelsLike": {
        "value": 17.6
      },
      "pressure": {
        "value": 1010
      },
      "uvIndex": {
        "value": 2.2
      },
      "cloudCover": {
        "value": 100,
        "high": 100,
        "middle": 100,
        "low": 72,
        "fog": 0
      },
      "humidity": {
        "value": 88.9
      },
      "dewPoint": {
        "value": 15.9
      },
      "start": "2025-09-01T17:00:00+02:00",
      "end": "2025-09-01T18:00:00+02:00"
    },
    {
      "symbol": {
        "n": 10,
        "clouds": 3,
        "precipPhase": "Rain",
        "precip": 3,
        "sunup": false
      },
      "symbolCode": {
        "next1Hour": "heavyrain",
        "next6Hours": "heavyrainshowers_night",
        "next12Hours": "lightrainshowers_night"
      },
      "precipitation": {
        "value": 4.7
      },
      "temperature": {
        "value": 17.1
      },
      "wind": {
        "direction": 205,
        "speed": 1.5
      },
      "feelsLike": {
        "value": 17.1
      },
      "pressure": {
        "value": 1011
      },
      "uvIndex": {
        "value": 1
      },
      "cloudCover": {
        "value": 100,
        "high": 100,
        "middle": 100,
        "low": 17,
        "fog": 0
      },
      "humidity": {
        "value": 91.9
      },
      "dewPoint": {
        "value": 15.9
      },
      "start": "2025-09-01T18:00:00+02:00",
      "end": "2025-09-01T19:00:00+02:00"
    },
    {
      "symbol": {
        "n": 10,
        "clouds": 3,
        "precipPhase": "Rain",
        "precip": 3,
        "sunup": false
      },
      "symbolCode": {
        "next1Hour": "heavyrain",
        "next6Hours": "rainshowers_night",
        "next12Hours": "lightrainshowers_night"
      },
      "precipitation": {
        "value": 1.3
      },
      "temperature": {
        "value": 16.8
      },
      "wind": {
        "direction": 205,
        "speed": 1.5
      },
      "feelsLike": {
        "value": 16.8
      },
      "pressure": {
        "value": 1011
      },
      "uvIndex": {
        "value": 0.3
      },
      "cloudCover": {
        "value": 100,
        "high": 100,
        "middle": 100,
        "low": 0,
        "fog": 0
      },
      "humidity": {
        "value": 94.1
      },
      "dewPoint": {
        "value": 16
      },
      "start": "2025-09-01T19:00:00+02:00",
      "end": "2025-09-01T20:00:00+02:00"
    },
    {
      "symbol": {
        "n": 40,
        "clouds": 2,
        "precipPhase": "Rain",
        "precip": 1,
        "var": "Moon",
        "sunup": false
      },
      "symbolCode": {
        "next1Hour": "lightrainshowers_night",
        "next6Hours": "partlycloudy_night",
        "next12Hours": "partlycloudy_night"
      },
      "precipitation": {
        "value": 0.1
      },
      "temperature": {
        "value": 16.6
      },
      "wind": {
        "direction": 217,
        "speed": 2.1
      },
      "feelsLike": {
        "value": 16.6
      },
      "pressure": {
        "value": 1011
      },
      "uvIndex": {
        "value": 0
      },
      "cloudCover": {
        "value": 78,
        "high": 44,
        "middle": 67,
        "low": 7,
        "fog": 0
      },
      "humidity": {
        "value": 94.2
      },
      "dewPoint": {
        "value": 15.8
      },
      "start": "2025-09-01T20:00:00+02:00",
      "end": "2025-09-01T21:00:00+02:00"
    },
    {
      "symbol": {
        "n": 3,
        "clouds": 2,
        "precip": 0,
        "var": "Moon",
        "sunup": false
      },
      "symbolCode": {
        "next1Hour": "partlycloudy_night",
        "next6Hours": "fair_night",
        "next12Hours": "partlycloudy_night"
      },
      "precipitation": {
        "value": 0
      },
      "temperature": {
        "value": 16
      },
      "wind": {
        "direction": 208,
        "speed": 2.1
      },
      "feelsLike": {
        "value": 16
      },
      "pressure": {
        "value": 1012
      },
      "uvIndex": {
        "value": 0
      },
      "cloudCover": {
        "value": 65,
        "high": 6,
        "middle": 58,
        "low": 10,
        "fog": 0
      },
      "humidity": {
        "value": 95.1
      },
      "dewPoint": {
        "value": 15.4
      },
      "start": "2025-09-01T21:00:00+02:00",
      "end": "2025-09-01T22:00:00+02:00"
    },
    {
      "symbol": {
        "n": 2,
        "clouds": 1,
        "precip": 0,
        "var": "Moon",
        "sunup": false
      },
      "symbolCode": {
        "next1Hour": "fair_night",
        "next6Hours": "partlycloudy_night",
        "next12Hours": "partlycloudy_day"
      },
      "precipitation": {
        "value": 0
      },
      "temperature": {
        "value": 15.2
      },
      "wind": {
        "direction": 214,
        "speed": 1.7
      },
      "feelsLike": {
        "value": 15.2
      },
      "pressure": {
        "value": 1013
      },
      "uvIndex": {
        "value": 0
      },
      "cloudCover": {
        "value": 37,
        "high": 1,
        "middle": 35,
        "low": 6,
        "fog": 0
      },
      "humidity": {
        "value": 95.3
      },
      "dewPoint": {
        "value": 14.6
      },
      "start": "2025-09-01T22:00:00+02:00",
      "end": "2025-09-01T23:00:00+02:00"
    },
    {
      "symbol": {
        "n": 2,
        "clouds": 1,
        "precip": 0,
        "var": "Moon",
        "sunup": false
      },
      "symbolCode": {
        "next1Hour": "fair_night",
        "next6Hours": "partlycloudy_night",
        "next12Hours": "partlycloudy_day"
      },
      "precipitation": {
        "value": 0
      },
      "temperature": {
        "value": 14.7
      },
      "wind": {
        "direction": 224,
        "speed": 1.8
      },
      "feelsLike": {
        "value": 15
      },
      "pressure": {
        "value": 1013
      },
      "uvIndex": {
        "value": 0
      },
      "cloudCover": {
        "value": 30,
        "high": 0,
        "middle": 29,
        "low": 6,
        "fog": 0
      },
      "humidity": {
        "value": 95.9
      },
      "dewPoint": {
        "value": 14.2
      },
      "start": "2025-09-01T23:00:00+02:00",
      "end": "2025-09-02T00:00:00+02:00"
    },
    {
      "symbol": {
        "n": 2,
        "clouds": 1,
        "precip": 0,
        "var": "Moon",
        "sunup": false
      },
      "symbolCode": {
        "next1Hour": "fair_night",
        "next6Hours": "partlycloudy_night",
        "next12Hours": "partlycloudy_day"
      },
      "precipitation": {
        "value": 0
      },
      "temperature": {
        "value": 14.3
      },
      "wind": {
        "direction": 232,
        "speed": 1.5
      },
      "feelsLike": {
        "value": 15
      },
      "pressure": {
        "value": 1013
      },
      "uvIndex": {
        "value": 0
      },
      "cloudCover": {
        "value": 29,
        "high": 0,
        "middle": 24,
        "low": 9,
        "fog": 0
      },
      "humidity": {
        "value": 95.6
      },
      "dewPoint": {
        "value": 13.7
      },
      "start": "2025-09-02T00:00:00+02:00",
      "end": "2025-09-02T01:00:00+02:00"
    },
    {
      "symbol": {
        "n": 2,
        "clouds": 1,
        "precip": 0,
        "var": "Moon",
        "sunup": false
      },
      "symbolCode": {
        "next1Hour": "fair_night",
        "next6Hours": "partlycloudy_night",
        "next12Hours": "partlycloudy_day"
      },
      "precipitation": {
        "value": 0
      },
      "temperature": {
        "value": 13.9
      },
      "wind": {
        "direction": 239,
        "speed": 1.6
      },
      "feelsLike": {
        "value": 14
      },
      "pressure": {
        "value": 1013
      },
      "uvIndex": {
        "value": 0
      },
      "cloudCover": {
        "value": 25,
        "high": 0,
        "middle": 20,
        "low": 13,
        "fog": 5
      },
      "humidity": {
        "value": 94.9
      },
      "dewPoint": {
        "value": 13.2
      },
      "start": "2025-09-02T01:00:00+02:00",
      "end": "2025-09-02T02:00:00+02:00"
    },
    {
      "symbol": {
        "n": 3,
        "clouds": 2,
        "precip": 0,
        "var": "Moon",
        "sunup": false
      },
      "symbolCode": {
        "next1Hour": "partlycloudy_night",
        "next6Hours": "partlycloudy_night",
        "next12Hours": "partlycloudy_day"
      },
      "precipitation": {
        "value": 0
      },
      "temperature": {
        "value": 13.2
      },
      "wind": {
        "direction": 234,
        "speed": 1.3
      },
      "feelsLike": {
        "value": 13.2
      },
      "pressure": {
        "value": 1014
      },
      "uvIndex": {
        "value": 0
      },
      "cloudCover": {
        "value": 48,
        "high": 0,
        "middle": 25,
        "low": 37,
        "fog": 24
      },
      "humidity": {
        "value": 94.8
      },
      "dewPoint": {
        "value": 12.5
      },
      "start": "2025-09-02T02:00:00+02:00",
      "end": "2025-09-02T03:00:00+02:00"
    },
    {
      "symbol": {
        "n": 3,
        "clouds": 2,
        "precip": 0,
        "var": "Moon",
        "sunup": false
      },
      "symbolCode": {
        "next1Hour": "partlycloudy_night",
        "next6Hours": "partlycloudy_night",
        "next12Hours": "partlycloudy_day"
      },
      "precipitation": {
        "value": 0
      },
      "temperature": {
        "value": 13.2
      },
      "wind": {
        "direction": 245,
        "speed": 1.3
      },
      "feelsLike": {
        "value": 13.2
      },
      "pressure": {
        "value": 1013
      },
      "uvIndex": {
        "value": 0
      },
      "cloudCover": {
        "value": 38,
        "high": 0,
        "middle": 28,
        "low": 18,
        "fog": 0
      },
      "humidity": {
        "value": 94
      },
      "dewPoint": {
        "value": 12.3
      },
      "start": "2025-09-02T03:00:00+02:00",
      "end": "2025-09-02T04:00:00+02:00"
    },
    {
      "symbol": {
        "n": 3,
        "clouds": 2,
        "precip": 0,
        "var": "Moon",
        "sunup": false
      },
      "symbolCode": {
        "next1Hour": "partlycloudy_night",
        "next6Hours": "partlycloudy_day",
        "next12Hours": "partlycloudy_day"
      },
      "precipitation": {
        "value": 0
      },
      "temperature": {
        "value": 13
      },
      "wind": {
        "direction": 219,
        "speed": 1.7
      },
      "feelsLike": {
        "value": 13
      },
      "pressure": {
        "value": 1014
      },
      "uvIndex": {
        "value": 0
      },
      "cloudCover": {
        "value": 74,
        "high": 0,
        "middle": 34,
        "low": 62,
        "fog": 6
      },
      "humidity": {
        "value": 93.3
      },
      "dewPoint": {
        "value": 12
      },
      "start": "2025-09-02T04:00:00+02:00",
      "end": "2025-09-02T05:00:00+02:00"
    },
    {
      "symbol": {
        "n": 3,
        "clouds": 2,
        "precip": 0,
        "var": "Moon",
        "sunup": false
      },
      "symbolCode": {
        "next1Hour": "partlycloudy_night",
        "next6Hours": "partlycloudy_day",
        "next12Hours": "partlycloudy_day"
      },
      "precipitation": {
        "value": 0
      },
      "temperature": {
        "value": 13.6
      },
      "wind": {
        "direction": 222,
        "speed": 2.1
      },
      "feelsLike": {
        "value": 13
      },
      "pressure": {
        "value": 1014
      },
      "uvIndex": {
        "value": 0
      },
      "cloudCover": {
        "value": 82,
        "high": 0,
        "middle": 42,
        "low": 70,
        "fog": 8
      },
      "humidity": {
        "value": 91.8
      },
      "dewPoint": {
        "value": 12.4
      },
      "start": "2025-09-02T05:00:00+02:00",
      "end": "2025-09-02T06:00:00+02:00"
    },
    {
      "symbol": {
        "n": 3,
        "clouds": 2,
        "precip": 0,
        "var": "Moon",
        "sunup": false
      },
      "symbolCode": {
        "next1Hour": "partlycloudy_night",
        "next6Hours": "fair_day",
        "next12Hours": "partlycloudy_day"
      },
      "precipitation": {
        "value": 0
      },
      "temperature": {
        "value": 13.3
      },
      "wind": {
        "direction": 219,
        "speed": 2
      },
      "feelsLike": {
        "value": 13
      },
      "pressure": {
        "value": 1014
      },
      "uvIndex": {
        "value": 0
      },
      "cloudCover": {
        "value": 84,
        "high": 0,
        "middle": 39,
        "low": 70,
        "fog": 8
      },
      "humidity": {
        "value": 92.4
      },
      "dewPoint": {
        "value": 12.2
      },
      "start": "2025-09-02T06:00:00+02:00",
      "end": "2025-09-02T07:00:00+02:00"
    },
    {
      "symbol": {
        "n": 3,
        "clouds": 2,
        "precip": 0,
        "var": "Sun",
        "sunup": false
      },
      "symbolCode": {
        "next1Hour": "partlycloudy_day",
        "next6Hours": "fair_day",
        "next12Hours": "partlycloudy_day"
      },
      "precipitation": {
        "value": 0
      },
      "temperature": {
        "value": 13.4
      },
      "wind": {
        "direction": 214,
        "speed": 1.8
      },
      "feelsLike": {
        "value": 13
      },
      "pressure": {
        "value": 1014
      },
      "uvIndex": {
        "value": 0
      },
      "cloudCover": {
        "value": 65,
        "high": 0,
        "middle": 35,
        "low": 48,
        "fog": 6
      },
      "humidity": {
        "value": 93.3
      },
      "dewPoint": {
        "value": 12.4
      },
      "start": "2025-09-02T07:00:00+02:00",
      "end": "2025-09-02T08:00:00+02:00"
    },
    {
      "symbol": {
        "n": 2,
        "clouds": 1,
        "precip": 0,
        "var": "Sun",
        "sunup": false
      },
      "symbolCode": {
        "next1Hour": "fair_day",
        "next6Hours": "fair_day",
        "next12Hours": "partlycloudy_day"
      },
      "precipitation": {
        "value": 0
      },
      "temperature": {
        "value": 13.8
      },
      "wind": {
        "direction": 217,
        "speed": 2.3
      },
      "feelsLike": {
        "value": 13
      },
      "pressure": {
        "value": 1014
      },
      "uvIndex": {
        "value": 0.3
      },
      "cloudCover": {
        "value": 31,
        "high": 0,
        "middle": 9,
        "low": 29,
        "fog": 6
      },
      "humidity": {
        "value": 92.9
      },
      "dewPoint": {
        "value": 12.8
      },
      "start": "2025-09-02T08:00:00+02:00",
      "end": "2025-09-02T09:00:00+02:00"
    },
    {
      "symbol": {
        "n": 2,
        "clouds": 1,
        "precip": 0,
        "var": "Sun",
        "sunup": false
      },
      "symbolCode": {
        "next1Hour": "fair_day",
        "next6Hours": "fair_day",
        "next12Hours": "partlycloudy_day"
      },
      "precipitation": {
        "value": 0
      },
      "temperature": {
        "value": 14.7
      },
      "wind": {
        "direction": 230,
        "speed": 2.5
      },
      "feelsLike": {
        "value": 14
      },
      "pressure": {
        "value": 1015
      },
      "uvIndex": {
        "value": 1
      },
      "cloudCover": {
        "value": 15,
        "high": 0,
        "middle": 4,
        "low": 14,
        "fog": 0
      },
      "humidity": {
        "value": 88.5
      },
      "dewPoint": {
        "value": 12.9
      },
      "start": "2025-09-02T09:00:00+02:00",
      "end": "2025-09-02T10:00:00+02:00"
    },
    {
      "symbol": {
        "n": 2,
        "clouds": 1,
        "precip": 0,
        "var": "Sun",
        "sunup": false
      },
      "symbolCode": {
        "next1Hour": "fair_day",
        "next6Hours": "fair_day",
        "next12Hours": "lightrainshowers_day"
      },
      "precipitation": {
        "value": 0
      },
      "temperature": {
        "value": 15.6
      },
      "wind": {
        "direction": 229,
        "speed": 2.3
      },
      "feelsLike": {
        "value": 15.6
      },
      "pressure": {
        "value": 1015
      },
      "uvIndex": {
        "value": 2.3
      },
      "cloudCover": {
        "value": 14,
        "high": 0,
        "middle": 6,
        "low": 12,
        "fog": 0
      },
      "humidity": {
        "value": 82
      },
      "dewPoint": {
        "value": 12.6
      },
      "start": "2025-09-02T10:00:00+02:00",
      "end": "2025-09-02T11:00:00+02:00"
    },
    {
      "symbol": {
        "n": 2,
        "clouds": 1,
        "precip": 0,
        "var": "Sun",
        "sunup": false
      },
      "symbolCode": {
        "next1Hour": "fair_day",
        "next6Hours": "partlycloudy_day",
        "next12Hours": "lightrainshowers_day"
      },
      "precipitation": {
        "value": 0
      },
      "temperature": {
        "value": 16.6
      },
      "wind": {
        "direction": 232,
        "speed": 2.2
      },
      "feelsLike": {
        "value": 16.6
      },
      "pressure": {
        "value": 1015
      },
      "uvIndex": {
        "value": 3.8
      },
      "cloudCover": {
        "value": 23,
        "high": 0,
        "middle": 8,
        "low": 21,
        "fog": 0
      },
      "humidity": {
        "value": 72.8
      },
      "dewPoint": {
        "value": 11.8
      },
      "start": "2025-09-02T11:00:00+02:00",
      "end": "2025-09-02T12:00:00+02:00"
    },
    {
      "symbol": {
        "n": 2,
        "clouds": 1,
        "precip": 0,
        "var": "Sun",
        "sunup": false
      },
      "symbolCode": {
        "next1Hour": "fair_day",
        "next6Hours": "partlycloudy_day",
        "next12Hours": "lightrainshowers_day"
      },
      "precipitation": {
        "value": 0
      },
      "temperature": {
        "value": 17.6
      },
      "wind": {
        "direction": 238,
        "speed": 2.4
      },
      "feelsLike": {
        "value": 17.6
      },
      "pressure": {
        "value": 1015
      },
      "uvIndex": {
        "value": 5.2
      },
      "cloudCover": {
        "value": 15,
        "high": 0,
        "middle": 8,
        "low": 12,
        "fog": 0
      },
      "humidity": {
        "value": 64.8
      },
      "dewPoint": {
        "value": 10.9
      },
      "start": "2025-09-02T12:00:00+02:00",
      "end": "2025-09-02T13:00:00+02:00"
    },
    {
      "symbol": {
        "n": 2,
        "clouds": 1,
        "precip": 0,
        "var": "Sun",
        "sunup": false
      },
      "symbolCode": {
        "next1Hour": "fair_day",
        "next6Hours": "partlycloudy_day",
        "next12Hours": "lightrain"
      },
      "precipitation": {
        "value": 0
      },
      "temperature": {
        "value": 18.6
      },
      "wind": {
        "direction": 225,
        "speed": 2.4
      },
      "feelsLike": {
        "value": 18.6
      },
      "pressure": {
        "value": 1014
      },
      "uvIndex": {
        "value": 6
      },
      "cloudCover": {
        "value": 16,
        "high": 0,
        "middle": 7,
        "low": 11,
        "fog": 0
      },
      "humidity": {
        "value": 58.8
      },
      "dewPoint": {
        "value": 10.4
      },
      "start": "2025-09-02T13:00:00+02:00",
      "end": "2025-09-02T14:00:00+02:00"
    },
    {
      "symbol": {
        "n": 3,
        "clouds": 2,
        "precip": 0,
        "var": "Sun",
        "sunup": false
      },
      "symbolCode": {
        "next1Hour": "partlycloudy_day",
        "next6Hours": "partlycloudy_day",
        "next12Hours": "lightrain"
      },
      "precipitation": {
        "value": 0
      },
      "temperature": {
        "value": 19.5
      },
      "wind": {
        "direction": 224,
        "speed": 3
      },
      "feelsLike": {
        "value": 19.5
      },
      "pressure": {
        "value": 1014
      },
      "uvIndex": {
        "value": 5.9
      },
      "cloudCover": {
        "value": 49,
        "high": 32,
        "middle": 19,
        "low": 9,
        "fog": 0
      },
      "humidity": {
        "value": 53.8
      },
      "dewPoint": {
        "value": 9.9
      },
      "start": "2025-09-02T14:00:00+02:00",
      "end": "2025-09-02T15:00:00+02:00"
    },
    {
      "symbol": {
        "n": 3,
        "clouds": 2,
        "precip": 0,
        "var": "Sun",
        "sunup": false
      },
      "symbolCode": {
        "next1Hour": "partlycloudy_day",
        "next6Hours": "cloudy",
        "next12Hours": "lightrain"
      },
      "precipitation": {
        "value": 0
      },
      "temperature": {
        "value": 20
      },
      "wind": {
        "direction": 201,
        "speed": 3.2
      },
      "feelsLike": {
        "value": 20
      },
      "pressure": {
        "value": 1013
      },
      "uvIndex": {
        "value": 5
      },
      "cloudCover": {
        "value": 64,
        "high": 45,
        "middle": 31,
        "low": 23,
        "fog": 0
      },
      "humidity": {
        "value": 52.2
      },
      "dewPoint": {
        "value": 9.9
      },
      "start": "2025-09-02T15:00:00+02:00",
      "end": "2025-09-02T16:00:00+02:00"
    },
    {
      "symbol": {
        "n": 2,
        "clouds": 1,
        "precip": 0,
        "var": "Sun",
        "sunup": false
      },
      "symbolCode": {
        "next1Hour": "fair_day",
        "next6Hours": "rain",
        "next12Hours": "lightrain"
      },
      "precipitation": {
        "value": 0
      },
      "temperature": {
        "value": 19.9
      },
      "wind": {
        "direction": 195,
        "speed": 3.9
      },
      "feelsLike": {
        "value": 19.9
      },
      "pressure": {
        "value": 1013
      },
      "uvIndex": {
        "value": 3.6
      },
      "cloudCover": {
        "value": 28,
        "high": 9,
        "middle": 20,
        "low": 6,
        "fog": 0
      },
      "humidity": {
        "value": 53.3
      },
      "dewPoint": {
        "value": 10.2
      },
      "start": "2025-09-02T16:00:00+02:00",
      "end": "2025-09-02T17:00:00+02:00"
    },
    {
      "symbol": {
        "n": 3,
        "clouds": 2,
        "precip": 0,
        "var": "Sun",
        "sunup": false
      },
      "symbolCode": {
        "next1Hour": "partlycloudy_day",
        "next6Hours": "rain",
        "next12Hours": "lightrain"
      },
      "precipitation": {
        "value": 0
      },
      "temperature": {
        "value": 19.6
      },
      "wind": {
        "direction": 195,
        "speed": 4.5
      },
      "feelsLike": {
        "value": 19.6
      },
      "pressure": {
        "value": 1013
      },
      "uvIndex": {
        "value": 2.1
      },
      "cloudCover": {
        "value": 100,
        "high": 100,
        "middle": 11,
        "low": 3,
        "fog": 0
      },
      "humidity": {
        "value": 55.7
      },
      "dewPoint": {
        "value": 10.5
      },
      "start": "2025-09-02T17:00:00+02:00",
      "end": "2025-09-02T18:00:00+02:00"
    },
    {
      "symbol": {
        "n": 3,
        "clouds": 2,
        "precip": 0,
        "var": "Sun",
        "sunup": false
      },
      "symbolCode": {
        "next1Hour": "partlycloudy_day",
        "next6Hours": "rain",
        "next12Hours": "lightrain"
      },
      "precipitation": {
        "value": 0
      },
      "temperature": {
        "value": 19
      },
      "wind": {
        "direction": 190,
        "speed": 4.1
      },
      "feelsLike": {
        "value": 19
      },
      "pressure": {
        "value": 1013
      },
      "uvIndex": {
        "value": 0.9
      },
      "cloudCover": {
        "value": 98,
        "high": 98,
        "middle": 5,
        "low": 2,
        "fog": 0
      },
      "humidity": {
        "value": 58.2
      },
      "dewPoint": {
        "value": 10.6
      },
      "start": "2025-09-02T18:00:00+02:00",
      "end": "2025-09-02T19:00:00+02:00"
    },
    {
      "symbol": {
        "n": 3,
        "clouds": 2,
        "precip": 0,
        "var": "Sun",
        "sunup": false
      },
      "symbolCode": {
        "next1Hour": "partlycloudy_day",
        "next6Hours": "rain",
        "next12Hours": "lightrainshowers_night"
      },
      "precipitation": {
        "value": 0
      },
      "temperature": {
        "value": 18.2
      },
      "wind": {
        "direction": 188,
        "speed": 2.9
      },
      "feelsLike": {
        "value": 18.2
      },
      "pressure": {
        "value": 1013
      },
      "uvIndex": {
        "value": 0.2
      },
      "cloudCover": {
        "value": 100,
        "high": 100,
        "middle": 1,
        "low": 1,
        "fog": 0
      },
      "humidity": {
        "value": 64.9
      },
      "dewPoint": {
        "value": 11.6
      },
      "start": "2025-09-02T19:00:00+02:00",
      "end": "2025-09-02T20:00:00+02:00"
    },
    {
      "symbol": {
        "n": 4,
        "clouds": 3,
        "precip": 0,
        "sunup": false
      },
      "symbolCode": {
        "next1Hour": "cloudy",
        "next6Hours": "rain",
        "next12Hours": "lightrainshowers_night"
      },
      "precipitation": {
        "value": 0
      },
      "temperature": {
        "value": 16.8
      },
      "wind": {
        "direction": 208,
        "speed": 2.1
      },
      "feelsLike": {
        "value": 16.8
      },
      "pressure": {
        "value": 1014
      },
      "uvIndex": {
        "value": 0
      },
      "cloudCover": {
        "value": 100,
        "high": 100,
        "middle": 75,
        "low": 0,
        "fog": 0
      },
      "humidity": {
        "value": 71.4
      },
      "dewPoint": {
        "value": 11.7
      },
      "start": "2025-09-02T20:00:00+02:00",
      "end": "2025-09-02T21:00:00+02:00"
    },
    {
      "symbol": {
        "n": 10,
        "clouds": 3,
        "precipPhase": "Rain",
        "precip": 3,
        "sunup": false
      },
      "symbolCode": {
        "next1Hour": "heavyrain",
        "next6Hours": "rain"
      },
      "precipitation": {
        "value": 1.3
      },
      "temperature": {
        "value": 16.4
      },
      "wind": {
        "direction": 220,
        "speed": 2
      },
      "feelsLike": {
        "value": 16.4
      },
      "pressure": {
        "value": 1014
      },
      "uvIndex": {
        "value": 0
      },
      "cloudCover": {
        "value": 100,
        "high": 91,
        "middle": 99,
        "low": 1,
        "fog": 0
      },
      "humidity": {
        "value": 74.5
      },
      "dewPoint": {
        "value": 11.9
      },
      "start": "2025-09-02T21:00:00+02:00",
      "end": "2025-09-02T22:00:00+02:00"
    },
    {
      "symbol": {
        "n": 4,
        "clouds": 3,
        "precip": 0,
        "sunup": false
      },
      "symbolCode": {
        "next1Hour": "cloudy",
        "next6Hours": "cloudy"
      },
      "precipitation": {
        "value": 0
      },
      "temperature": {
        "value": 16.2
      },
      "wind": {
        "direction": 245,
        "speed": 2.2
      },
      "feelsLike": {
        "value": 16.2
      },
      "pressure": {
        "value": 1015
      },
      "uvIndex": {
        "value": 0
      },
      "cloudCover": {
        "value": 99,
        "high": 97,
        "middle": 82,
        "low": 9,
        "fog": 0
      },
      "humidity": {
        "value": 78.9
      },
      "dewPoint": {
        "value": 12.6
      },
      "start": "2025-09-02T22:00:00+02:00",
      "end": "2025-09-02T23:00:00+02:00"
    },
    {
      "symbol": {
        "n": 4,
        "clouds": 3,
        "precip": 0,
        "sunup": false
      },
      "symbolCode": {
        "next1Hour": "cloudy",
        "next6Hours": "cloudy"
      },
      "precipitation": {
        "value": 0
      },
      "temperature": {
        "value": 15.6
      },
      "wind": {
        "direction": 222,
        "speed": 2.1
      },
      "feelsLike": {
        "value": 15.6
      },
      "pressure": {
        "value": 1016
      },
      "uvIndex": {
        "value": 0
      },
      "cloudCover": {
        "value": 99,
        "high": 95,
        "middle": 94,
        "low": 9,
        "fog": 0
      },
      "humidity": {
        "value": 79.9
      },
      "dewPoint": {
        "value": 12.2
      },
      "start": "2025-09-02T23:00:00+02:00",
      "end": "2025-09-03T00:00:00+02:00"
    },
    {
      "symbol": {
        "n": 4,
        "clouds": 3,
        "precip": 0,
        "sunup": false
      },
      "symbolCode": {
        "next1Hour": "cloudy",
        "next6Hours": "partlycloudy_night"
      },
      "precipitation": {
        "value": 0
      },
      "temperature": {
        "value": 15.7
      },
      "wind": {
        "direction": 228,
        "speed": 2
      },
      "feelsLike": {
        "value": 15.7
      },
      "pressure": {
        "value": 1015
      },
      "uvIndex": {
        "value": 0
      },
      "cloudCover": {
        "value": 100,
        "high": 100,
        "middle": 85,
        "low": 5,
        "fog": 0
      },
      "humidity": {
        "value": 77.7
      },
      "dewPoint": {
        "value": 11.9
      },
      "start": "2025-09-03T00:00:00+02:00",
      "end": "2025-09-03T01:00:00+02:00"
    },
    {
      "symbol": {
        "n": 4,
        "clouds": 3,
        "precip": 0,
        "sunup": false
      },
      "symbolCode": {
        "next1Hour": "cloudy",
        "next6Hours": "partlycloudy_night"
      },
      "precipitation": {
        "value": 0
      },
      "temperature": {
        "value": 15.5
      },
      "wind": {
        "direction": 232,
        "speed": 2.1
      },
      "feelsLike": {
        "value": 15.5
      },
      "pressure": {
        "value": 1016
      },
      "uvIndex": {
        "value": 0
      },
      "cloudCover": {
        "value": 100,
        "high": 100,
        "middle": 60,
        "low": 9,
        "fog": 0
      },
      "humidity": {
        "value": 76.5
      },
      "dewPoint": {
        "value": 11.4
      },
      "start": "2025-09-03T01:00:00+02:00",
      "end": "2025-09-03T02:00:00+02:00"
    },
    {
      "symbol": {
        "n": 4,
        "clouds": 3,
        "precip": 0,
        "sunup": false
      },
      "symbolCode": {
        "next1Hour": "cloudy",
        "next6Hours": "partlycloudy_night",
        "next12Hours": "partlycloudy_day"
      },
      "precipitation": {
        "value": 0
      },
      "temperature": {
        "value": 15.5
      },
      "wind": {
        "direction": 233,
        "speed": 2
      },
      "feelsLike": {
        "value": 15.5
      },
      "pressure": {
        "value": 1016
      },
      "uvIndex": {
        "value": 0
      },
      "cloudCover": {
        "value": 100,
        "high": 67,
        "middle": 100,
        "low": 91,
        "fog": 0
      },
      "humidity": {
        "value": 74.3
      },
      "dewPoint": {
        "value": 11
      },
      "start": "2025-09-03T02:00:00+02:00",
      "end": "2025-09-03T03:00:00+02:00"
    },
    {
      "symbol": {
        "n": 3,
        "clouds": 2,
        "precip": 0,
        "var": "Moon",
        "sunup": false
      },
      "symbolCode": {
        "next1Hour": "partlycloudy_night"
      },
      "precipitation": {
        "value": 0
      },
      "temperature": {
        "value": 15.9
      },
      "wind": {
        "direction": 230,
        "speed": 2.3
      },
      "feelsLike": {
        "value": 15.9
      },
      "pressure": {
        "value": 1016
      },
      "uvIndex": {
        "value": 0
      },
      "cloudCover": {
        "value": 76,
        "high": 20,
        "middle": 45,
        "low": 58,
        "fog": 0
      },
      "humidity": {
        "value": 73.2
      },
      "dewPoint": {
        "value": 11.2
      },
      "start": "2025-09-03T03:00:00+02:00",
      "end": "2025-09-03T04:00:00+02:00"
    },
    {
      "symbol": {
        "n": 3,
        "clouds": 2,
        "precip": 0,
        "var": "Moon",
        "sunup": false
      },
      "symbolCode": {
        "next1Hour": "partlycloudy_night"
      },
      "precipitation": {
        "value": 0
      },
      "temperature": {
        "value": 15.6
      },
      "wind": {
        "direction": 225,
        "speed": 2.4
      },
      "feelsLike": {
        "value": 15.6
      },
      "pressure": {
        "value": 1016
      },
      "uvIndex": {
        "value": 0
      },
      "cloudCover": {
        "value": 66,
        "high": 34,
        "middle": 21,
        "low": 46,
        "fog": 0
      },
      "humidity": {
        "value": 75.9
      },
      "dewPoint": {
        "value": 11.4
      },
      "start": "2025-09-03T04:00:00+02:00",
      "end": "2025-09-03T05:00:00+02:00"
    },
    {
      "symbol": {
        "n": 4,
        "clouds": 3,
        "precip": 0,
        "sunup": false
      },
      "symbolCode": {
        "next1Hour": "cloudy"
      },
      "precipitation": {
        "value": 0
      },
      "temperature": {
        "value": 14.5
      },
      "wind": {
        "direction": 220,
        "speed": 2.5
      },
      "feelsLike": {
        "value": 14
      },
      "pressure": {
        "value": 1016
      },
      "uvIndex": {
        "value": 0
      },
      "cloudCover": {
        "value": 92,
        "high": 91,
        "middle": 16,
        "low": 9,
        "fog": 0
      },
      "humidity": {
        "value": 79.8
      },
      "dewPoint": {
        "value": 11.1
      },
      "start": "2025-09-03T05:00:00+02:00",
      "end": "2025-09-03T06:00:00+02:00"
    },
    {
      "symbol": {
        "n": 2,
        "clouds": 1,
        "precip": 0,
        "var": "Moon",
        "sunup": false
      },
      "symbolCode": {
        "next1Hour": "fair_night"
      },
      "precipitation": {
        "value": 0
      },
      "temperature": {
        "value": 14.1
      },
      "wind": {
        "direction": 228,
        "speed": 2.2
      },
      "feelsLike": {
        "value": 14
      },
      "pressure": {
        "value": 1016
      },
      "uvIndex": {
        "value": 0
      },
      "cloudCover": {
        "value": 27,
        "high": 9,
        "middle": 14,
        "low": 9,
        "fog": 0
      },
      "humidity": {
        "value": 82.5
      },
      "dewPoint": {
        "value": 11.2
      },
      "start": "2025-09-03T06:00:00+02:00",
      "end": "2025-09-03T07:00:00+02:00"
    },
    {
      "symbol": {
        "n": 2,
        "clouds": 1,
        "precip": 0,
        "var": "Sun",
        "sunup": false
      },
      "symbolCode": {
        "next1Hour": "fair_day"
      },
      "precipitation": {
        "value": 0
      },
      "temperature": {
        "value": 13.7
      },
      "wind": {
        "direction": 234,
        "speed": 1.7
      },
      "feelsLike": {
        "value": 14
      },
      "pressure": {
        "value": 1017
      },
      "uvIndex": {
        "value": 0
      },
      "cloudCover": {
        "value": 18,
        "high": 3,
        "middle": 15,
        "low": 6,
        "fog": 0
      },
      "humidity": {
        "value": 83.6
      },
      "dewPoint": {
        "value": 11
      },
      "start": "2025-09-03T07:00:00+02:00",
      "end": "2025-09-03T08:00:00+02:00"
    }
  ],
  "longIntervals": [
    {
      "symbol": {
        "n": 10,
        "clouds": 3,
        "precipPhase": "Rain",
        "precip": 3,
        "sunup": false
      },
      "symbolCode": {
        "next1Hour": "cloudy",
        "next6Hours": "heavyrain",
        "next12Hours": "heavyrain"
      },
      "precipitation": {
        "value": 5.5
      },
      "temperature": {
        "value": 20.4,
        "min": 17.1,
        "max": 20.2
      },
      "wind": {
        "direction": 126,
        "speed": 0.6
      },
      "feelsLike": {
        "value": 20.4
      },
      "pressure": {
        "value": 1010
      },
      "cloudCover": {
        "value": 99,
        "high": 98,
        "middle": 53,
        "low": 0,
        "fog": 0
      },
      "humidity": {
        "value": 72.7
      },
      "dewPoint": {
        "value": 15.5
      },
      "start": "2025-08-31T21:00:00+02:00",
      "end": "2025-09-01T00:00:00+02:00",
      "nominalStart": "2025-08-31T18:00:00+02:00",
      "nominalEnd": "2025-09-01T00:00:00+02:00"
    },
    {
      "symbol": {
        "n": 10,
        "clouds": 3,
        "precipPhase": "Rain",
        "precip": 3,
        "sunup": false
      },
      "symbolCode": {
        "next1Hour": "cloudy",
        "next6Hours": "heavyrain",
        "next12Hours": "rain"
      },
      "precipitation": {
        "value": 15.7
      },
      "temperature": {
        "value": 18.8,
        "min": 16.6,
        "max": 18.6
      },
      "wind": {
        "direction": 212,
        "speed": 1.6
      },
      "feelsLike": {
        "value": 18.8
      },
      "pressure": {
        "value": 1010
      },
      "cloudCover": {
        "value": 99,
        "high": 98,
        "middle": 73,
        "low": 1,
        "fog": 0
      },
      "humidity": {
        "value": 78.2
      },
      "dewPoint": {
        "value": 15.1
      },
      "start": "2025-09-01T00:00:00+02:00",
      "end": "2025-09-01T06:00:00+02:00",
      "nominalStart": "2025-09-01T00:00:00+02:00",
      "nominalEnd": "2025-09-01T06:00:00+02:00"
    },
    {
      "symbol": {
        "n": 9,
        "clouds": 3,
        "precipPhase": "Rain",
        "precip": 2,
        "sunup": false
      },
      "symbolCode": {
        "next1Hour": "rain",
        "next6Hours": "rain",
        "next12Hours": "rain"
      },
      "precipitation": {
        "value": 2.6
      },
      "temperature": {
        "value": 16.6,
        "min": 16.4,
        "max": 19.2
      },
      "wind": {
        "direction": 183,
        "speed": 1.9
      },
      "feelsLike": {
        "value": 16.6
      },
      "pressure": {
        "value": 1010
      },
      "cloudCover": {
        "value": 100,
        "high": 40,
        "middle": 100,
        "low": 24,
        "fog": 0
      },
      "humidity": {
        "value": 93.9
      },
      "dewPoint": {
        "value": 15.8
      },
      "start": "2025-09-01T06:00:00+02:00",
      "end": "2025-09-01T12:00:00+02:00",
      "nominalStart": "2025-09-01T06:00:00+02:00",
      "nominalEnd": "2025-09-01T12:00:00+02:00"
    },
    {
      "symbol": {
        "n": 10,
        "clouds": 3,
        "precipPhase": "Rain",
        "precip": 3,
        "sunup": false
      },
      "symbolCode": {
        "next1Hour": "partlycloudy_day",
        "next6Hours": "heavyrain",
        "next12Hours": "heavyrainshowers_day"
      },
      "precipitation": {
        "value": 13.1
      },
      "temperature": {
        "value": 19.2,
        "min": 17.1,
        "max": 20.9
      },
      "wind": {
        "direction": 236,
        "speed": 2
      },
      "feelsLike": {
        "value": 19.2
      },
      "pressure": {
        "value": 1011
      },
      "cloudCover": {
        "value": 75,
        "high": 46,
        "middle": 25,
        "low": 44,
        "fog": 0
      },
      "humidity": {
        "value": 80
      },
      "dewPoint": {
        "value": 15.8
      },
      "start": "2025-09-01T12:00:00+02:00",
      "end": "2025-09-01T18:00:00+02:00",
      "nominalStart": "2025-09-01T12:00:00+02:00",
      "nominalEnd": "2025-09-01T18:00:00+02:00"
    },
    {
      "symbol": {
        "n": 41,
        "clouds": 2,
        "precipPhase": "Rain",
        "precip": 3,
        "var": "Moon",
        "sunup": false
      },
      "symbolCode": {
        "next1Hour": "heavyrain",
        "next6Hours": "heavyrainshowers_night",
        "next12Hours": "lightrainshowers_night"
      },
      "precipitation": {
        "value": 6.1
      },
      "temperature": {
        "value": 17.1,
        "min": 14.3,
        "max": 16.8
      },
      "wind": {
        "direction": 205,
        "speed": 1.5
      },
      "feelsLike": {
        "value": 17.1
      },
      "pressure": {
        "value": 1011
      },
      "cloudCover": {
        "value": 100,
        "high": 100,
        "middle": 100,
        "low": 17,
        "fog": 0
      },
      "humidity": {
        "value": 91.9
      },
      "dewPoint": {
        "value": 15.9
      },
      "start": "2025-09-01T18:00:00+02:00",
      "end": "2025-09-02T00:00:00+02:00",
      "nominalStart": "2025-09-01T18:00:00+02:00",
      "nominalEnd": "2025-09-02T00:00:00+02:00"
    },
    {
      "symbol": {
        "n": 3,
        "clouds": 2,
        "precip": 0,
        "var": "Moon",
        "sunup": false
      },
      "symbolCode": {
        "next1Hour": "fair_night",
        "next6Hours": "partlycloudy_night",
        "next12Hours": "partlycloudy_day"
      },
      "precipitation": {
        "value": 0.1
      },
      "temperature": {
        "value": 14.3,
        "min": 13,
        "max": 13.9
      },
      "wind": {
        "direction": 232,
        "speed": 1.5
      },
      "feelsLike": {
        "value": 15
      },
      "pressure": {
        "value": 1013
      },
      "cloudCover": {
        "value": 29,
        "high": 0,
        "middle": 24,
        "low": 9,
        "fog": 0
      },
      "humidity": {
        "value": 95.6
      },
      "dewPoint": {
        "value": 13.7
      },
      "start": "2025-09-02T00:00:00+02:00",
      "end": "2025-09-02T06:00:00+02:00",
      "nominalStart": "2025-09-02T00:00:00+02:00",
      "nominalEnd": "2025-09-02T06:00:00+02:00"
    },
    {
      "symbol": {
        "n": 2,
        "clouds": 1,
        "precip": 0,
        "var": "Sun",
        "sunup": false
      },
      "symbolCode": {
        "next1Hour": "partlycloudy_night",
        "next6Hours": "fair_day",
        "next12Hours": "partlycloudy_day"
      },
      "precipitation": {
        "value": 0.3
      },
      "temperature": {
        "value": 13.3,
        "min": 13.4,
        "max": 17.6
      },
      "wind": {
        "direction": 219,
        "speed": 2
      },
      "feelsLike": {
        "value": 13
      },
      "pressure": {
        "value": 1014
      },
      "cloudCover": {
        "value": 84,
        "high": 0,
        "middle": 39,
        "low": 70,
        "fog": 8
      },
      "humidity": {
        "value": 92.4
      },
      "dewPoint": {
        "value": 12.2
      },
      "start": "2025-09-02T06:00:00+02:00",
      "end": "2025-09-02T12:00:00+02:00",
      "nominalStart": "2025-09-02T06:00:00+02:00",
      "nominalEnd": "2025-09-02T12:00:00+02:00"
    },
    {
      "symbol": {
        "n": 3,
        "clouds": 2,
        "precip": 0,
        "var": "Sun",
        "sunup": false
      },
      "symbolCode": {
        "next1Hour": "fair_day",
        "next6Hours": "partlycloudy_day",
        "next12Hours": "lightrainshowers_day"
      },
      "precipitation": {
        "value": 0.1
      },
      "temperature": {
        "value": 17.6,
        "min": 18.6,
        "max": 20
      },
      "wind": {
        "direction": 238,
        "speed": 2.4
      },
      "feelsLike": {
        "value": 17.6
      },
      "pressure": {
        "value": 1015
      },
      "cloudCover": {
        "value": 15,
        "high": 0,
        "middle": 8,
        "low": 12,
        "fog": 0
      },
      "humidity": {
        "value": 64.8
      },
      "dewPoint": {
        "value": 10.9
      },
      "start": "2025-09-02T12:00:00+02:00",
      "end": "2025-09-02T18:00:00+02:00",
      "nominalStart": "2025-09-02T12:00:00+02:00",
      "nominalEnd": "2025-09-02T18:00:00+02:00"
    },
    {
      "symbol": {
        "n": 9,
        "clouds": 3,
        "precipPhase": "Rain",
        "precip": 2,
        "sunup": false
      },
      "symbolCode": {
        "next1Hour": "partlycloudy_day",
        "next6Hours": "rain",
        "next12Hours": "lightrain"
      },
      "precipitation": {
        "value": 1.3
      },
      "temperature": {
        "value": 19,
        "min": 15.6,
        "max": 18.2
      },
      "wind": {
        "direction": 190,
        "speed": 4.1
      },
      "feelsLike": {
        "value": 19
      },
      "pressure": {
        "value": 1013
      },
      "cloudCover": {
        "value": 98,
        "high": 98,
        "middle": 5,
        "low": 2,
        "fog": 0
      },
      "humidity": {
        "value": 58.2
      },
      "dewPoint": {
        "value": 10.6
      },
      "start": "2025-09-02T18:00:00+02:00",
      "end": "2025-09-03T00:00:00+02:00",
      "nominalStart": "2025-09-02T18:00:00+02:00",
      "nominalEnd": "2025-09-03T00:00:00+02:00"
    },
    {
      "symbol": {
        "n": 3,
        "clouds": 2,
        "precip": 0,
        "var": "Moon",
        "sunup": false
      },
      "symbolCode": {
        "next1Hour": "cloudy",
        "next6Hours": "partlycloudy_night"
      },
      "precipitation": {
        "value": 0
      },
      "temperature": {
        "value": 15.7,
        "min": 14.1,
        "max": 15.9
      },
      "wind": {
        "direction": 228,
        "speed": 2
      },
      "feelsLike": {
        "value": 15.7
      },
      "pressure": {
        "value": 1015
      },
      "cloudCover": {
        "value": 100,
        "high": 100,
        "middle": 85,
        "low": 5,
        "fog": 0
      },
      "humidity": {
        "value": 77.7
      },
      "dewPoint": {
        "value": 11.9
      },
      "start": "2025-09-03T00:00:00+02:00",
      "end": "2025-09-03T06:00:00+02:00",
      "nominalStart": "2025-09-03T00:00:00+02:00",
      "nominalEnd": "2025-09-03T06:00:00+02:00"
    },
    {
      "symbol": {
        "n": 3,
        "clouds": 2,
        "precip": 0,
        "var": "Sun",
        "sunup": false
      },
      "symbolCode": {
        "next6Hours": "partlycloudy_day",
        "next12Hours": "partlycloudy_day"
      },
      "precipitation": {
        "value": 0.1
      },
      "temperature": {
        "value": 14.9,
        "min": 14.8,
        "max": 21.3
      },
      "wind": {
        "direction": 233,
        "speed": 1.6
      },
      "feelsLike": {
        "value": 15
      },
      "pressure": {
        "value": 1017
      },
      "uvIndex": {
        "value": 0.3
      },
      "cloudCover": {
        "value": 24,
        "high": 0,
        "middle": 20,
        "low": 11,
        "fog": 0
      },
      "humidity": {
        "value": 83.1
      },
      "dewPoint": {
        "value": 12.1
      },
      "start": "2025-09-03T08:00:00+02:00",
      "end": "2025-09-03T14:00:00+02:00",
      "nominalStart": "2025-09-03T06:00:00+02:00",
      "nominalEnd": "2025-09-03T12:00:00+02:00"
    },
    {
      "symbol": {
        "n": 2,
        "clouds": 1,
        "precip": 0,
        "var": "Sun",
        "sunup": false
      },
      "symbolCode": {
        "next6Hours": "fair_day",
        "next12Hours": "fair_day"
      },
      "precipitation": {
        "value": 0
      },
      "temperature": {
        "value": 21.3,
        "min": 18.8,
        "max": 22.3
      },
      "wind": {
        "direction": 203,
        "speed": 2.8
      },
      "feelsLike": {
        "value": 21.3
      },
      "pressure": {
        "value": 1016
      },
      "cloudCover": {
        "value": 28,
        "high": 0,
        "middle": 2,
        "low": 27,
        "fog": 0
      },
      "humidity": {
        "value": 63.3
      },
      "dewPoint": {
        "value": 14.2
      },
      "start": "2025-09-03T14:00:00+02:00",
      "end": "2025-09-03T20:00:00+02:00",
      "nominalStart": "2025-09-03T12:00:00+02:00",
      "nominalEnd": "2025-09-03T18:00:00+02:00"
    },
    {
      "symbol": {
        "n": 2,
        "clouds": 1,
        "precip": 0,
        "var": "Moon",
        "sunup": false
      },
      "symbolCode": {
        "next6Hours": "fair_night",
        "next12Hours": "clearsky_night"
      },
      "precipitation": {
        "value": 0
      },
      "temperature": {
        "value": 18.8,
        "min": 15.7,
        "max": 18.8
      },
      "wind": {
        "direction": 220,
        "speed": 1.5
      },
      "feelsLike": {
        "value": 18.8
      },
      "pressure": {
        "value": 1015
      },
      "cloudCover": {
        "value": 14,
        "high": 5,
        "middle": 13,
        "low": 0,
        "fog": 0
      },
      "humidity": {
        "value": 80.1
      },
      "dewPoint": {
        "value": 15.4
      },
      "start": "2025-09-03T20:00:00+02:00",
      "end": "2025-09-04T02:00:00+02:00",
      "nominalStart": "2025-09-03T18:00:00+02:00",
      "nominalEnd": "2025-09-04T00:00:00+02:00"
    },
    {
      "symbol": {
        "n": 1,
        "clouds": 0,
        "precip": 0,
        "var": "Moon",
        "sunup": false
      },
      "symbolCode": {
        "next6Hours": "clearsky_night",
        "next12Hours": "rainshowers_day"
      },
      "precipitation": {
        "value": 0
      },
      "temperature": {
        "value": 15.7,
        "min": 14.6,
        "max": 16.2
      },
      "wind": {
        "direction": 230,
        "speed": 0.5
      },
      "feelsLike": {
        "value": 15.7
      },
      "pressure": {
        "value": 1015
      },
      "cloudCover": {
        "value": 0,
        "high": 0,
        "middle": 0,
        "low": 0,
        "fog": 0
      },
      "humidity": {
        "value": 83.3
      },
      "dewPoint": {
        "value": 13
      },
      "start": "2025-09-04T02:00:00+02:00",
      "end": "2025-09-04T08:00:00+02:00",
      "nominalStart": "2025-09-04T00:00:00+02:00",
      "nominalEnd": "2025-09-04T06:00:00+02:00"
    },
    {
      "symbol": {
        "n": 41,
        "clouds": 2,
        "precipPhase": "Rain",
        "precip": 3,
        "var": "Sun",
        "sunup": false
      },
      "symbolCode": {
        "next6Hours": "heavyrainshowers_day",
        "next12Hours": "rainshowers_day"
      },
      "precipitation": {
        "value": 5.9
      },
      "temperature": {
        "value": 16.2,
        "min": 16.2,
        "max": 19.9
      },
      "wind": {
        "direction": 237,
        "speed": 0.4
      },
      "feelsLike": {
        "value": 16.2
      },
      "pressure": {
        "value": 1015
      },
      "cloudCover": {
        "value": 26,
        "high": 12,
        "middle": 16,
        "low": 0,
        "fog": 0
      },
      "humidity": {
        "value": 83.7
      },
      "dewPoint": {
        "value": 13.5
      },
      "start": "2025-09-04T08:00:00+02:00",
      "end": "2025-09-04T14:00:00+02:00",
      "nominalStart": "2025-09-04T06:00:00+02:00",
      "nominalEnd": "2025-09-04T12:00:00+02:00"
    },
    {
      "symbol": {
        "n": 9,
        "clouds": 3,
        "precipPhase": "Rain",
        "precip": 2,
        "sunup": false
      },
      "symbolCode": {
        "next6Hours": "rain",
        "next12Hours": "lightrainshowers_day"
      },
      "precipitation": {
        "value": 2.7
      },
      "temperature": {
        "value": 17.9,
        "min": 16.6,
        "max": 18.5
      },
      "wind": {
        "direction": 332,
        "speed": 1.4
      },
      "feelsLike": {
        "value": 17.9
      },
      "pressure": {
        "value": 1020
      },
      "cloudCover": {
        "value": 100,
        "high": 98,
        "middle": 59,
        "low": 65,
        "fog": 0
      },
      "humidity": {
        "value": 88.3
      },
      "dewPoint": {
        "value": 16.1
      },
      "start": "2025-09-04T14:00:00+02:00",
      "end": "2025-09-04T20:00:00+02:00",
      "nominalStart": "2025-09-04T12:00:00+02:00",
      "nominalEnd": "2025-09-04T18:00:00+02:00"
    },
    {
      "symbol": {
        "n": 2,
        "clouds": 1,
        "precip": 0,
        "var": "Moon",
        "sunup": false
      },
      "symbolCode": {
        "next6Hours": "fair_night",
        "next12Hours": "partlycloudy_night"
      },
      "precipitation": {
        "value": 0.1
      },
      "temperature": {
        "value": 16.6,
        "min": 13.2,
        "max": 16.6
      },
      "wind": {
        "direction": 209,
        "speed": 0.5
      },
      "feelsLike": {
        "value": 16.6
      },
      "pressure": {
        "value": 1021
      },
      "cloudCover": {
        "value": 31,
        "high": 0,
        "middle": 30,
        "low": 2,
        "fog": 0
      },
      "humidity": {
        "value": 87.1
      },
      "dewPoint": {
        "value": 14.6
      },
      "start": "2025-09-04T20:00:00+02:00",
      "end": "2025-09-05T02:00:00+02:00",
      "nominalStart": "2025-09-04T18:00:00+02:00",
      "nominalEnd": "2025-09-05T00:00:00+02:00"
    },
    {
      "symbol": {
        "n": 3,
        "clouds": 2,
        "precip": 0,
        "var": "Moon",
        "sunup": false
      },
      "symbolCode": {
        "next6Hours": "partlycloudy_night",
        "next12Hours": "partlycloudy_day"
      },
      "precipitation": {
        "value": 0.1
      },
      "temperature": {
        "value": 13.2,
        "min": 12.4,
        "max": 14.5
      },
      "wind": {
        "direction": 352,
        "speed": 0.4
      },
      "feelsLike": {
        "value": 13.2
      },
      "pressure": {
        "value": 1023
      },
      "cloudCover": {
        "value": 51,
        "high": 0,
        "middle": 14,
        "low": 45,
        "fog": 0
      },
      "humidity": {
        "value": 93
      },
      "dewPoint": {
        "value": 12.2
      },
      "start": "2025-09-05T02:00:00+02:00",
      "end": "2025-09-05T08:00:00+02:00",
      "nominalStart": "2025-09-05T00:00:00+02:00",
      "nominalEnd": "2025-09-05T06:00:00+02:00"
    },
    {
      "symbol": {
        "n": 3,
        "clouds": 2,
        "precip": 0,
        "var": "Sun",
        "sunup": false
      },
      "symbolCode": {
        "next6Hours": "partlycloudy_day",
        "next12Hours": "fair_day"
      },
      "precipitation": {
        "value": 0.1
      },
      "temperature": {
        "value": 14.5,
        "min": 14.4,
        "max": 19.8
      },
      "wind": {
        "direction": 16,
        "speed": 1.5
      },
      "feelsLike": {
        "value": 15
      },
      "pressure": {
        "value": 1023
      },
      "cloudCover": {
        "value": 74,
        "high": 0,
        "middle": 0,
        "low": 74,
        "fog": 0
      },
      "humidity": {
        "value": 89.3
      },
      "dewPoint": {
        "value": 12.8
      },
      "start": "2025-09-05T08:00:00+02:00",
      "end": "2025-09-05T14:00:00+02:00",
      "nominalStart": "2025-09-05T06:00:00+02:00",
      "nominalEnd": "2025-09-05T12:00:00+02:00"
    },
    {
      "symbol": {
        "n": 1,
        "clouds": 0,
        "precip": 0,
        "var": "Sun",
        "sunup": false
      },
      "symbolCode": {
        "next6Hours": "clearsky_day",
        "next12Hours": "clearsky_day"
      },
      "precipitation": {
        "value": 0
      },
      "temperature": {
        "value": 19.8,
        "min": 16.9,
        "max": 20.1
      },
      "wind": {
        "direction": 49,
        "speed": 3
      },
      "feelsLike": {
        "value": 19.8
      },
      "pressure": {
        "value": 1022
      },
      "cloudCover": {
        "value": 9,
        "high": 0,
        "middle": 0,
        "low": 9,
        "fog": 0
      },
      "humidity": {
        "value": 68.4
      },
      "dewPoint": {
        "value": 13.9
      },
      "start": "2025-09-05T14:00:00+02:00",
      "end": "2025-09-05T20:00:00+02:00",
      "nominalStart": "2025-09-05T12:00:00+02:00",
      "nominalEnd": "2025-09-05T18:00:00+02:00"
    },
    {
      "symbol": {
        "n": 1,
        "clouds": 0,
        "precip": 0,
        "var": "Moon",
        "sunup": false
      },
      "symbolCode": {
        "next6Hours": "clearsky_night",
        "next12Hours": "clearsky_night"
      },
      "precipitation": {
        "value": 0
      },
      "temperature": {
        "value": 16.9,
        "min": 14,
        "max": 16.9
      },
      "wind": {
        "direction": 358,
        "speed": 1.2
      },
      "feelsLike": {
        "value": 16.9
      },
      "pressure": {
        "value": 1021
      },
      "cloudCover": {
        "value": 2,
        "high": 0,
        "middle": 0,
        "low": 2,
        "fog": 0
      },
      "humidity": {
        "value": 82.8
      },
      "dewPoint": {
        "value": 14.1
      },
      "start": "2025-09-05T20:00:00+02:00",
      "end": "2025-09-06T02:00:00+02:00",
      "nominalStart": "2025-09-05T18:00:00+02:00",
      "nominalEnd": "2025-09-06T00:00:00+02:00"
    },
    {
      "symbol": {
        "n": 1,
        "clouds": 0,
        "precip": 0,
        "var": "Moon",
        "sunup": false
      },
      "symbolCode": {
        "next6Hours": "clearsky_night",
        "next12Hours": "clearsky_day"
      },
      "precipitation": {
        "value": 0
      },
      "temperature": {
        "value": 14,
        "min": 12.5,
        "max": 14
      },
      "wind": {
        "direction": 17,
        "speed": 0.8
      },
      "feelsLike": {
        "value": 14
      },
      "pressure": {
        "value": 1022
      },
      "cloudCover": {
        "value": 1,
        "high": 1,
        "middle": 0,
        "low": 0,
        "fog": 0
      },
      "humidity": {
        "value": 86.3
      },
      "dewPoint": {
        "value": 11.8
      },
      "start": "2025-09-06T02:00:00+02:00",
      "end": "2025-09-06T08:00:00+02:00",
      "nominalStart": "2025-09-06T00:00:00+02:00",
      "nominalEnd": "2025-09-06T06:00:00+02:00"
    },
    {
      "symbol": {
        "n": 2,
        "clouds": 1,
        "precip": 0,
        "var": "Sun",
        "sunup": false
      },
      "symbolCode": {
        "next6Hours": "fair_day",
        "next12Hours": "clearsky_day"
      },
      "precipitation": {
        "value": 0
      },
      "temperature": {
        "value": 13.6,
        "min": 13.6,
        "max": 22.3
      },
      "wind": {
        "direction": 59,
        "speed": 0.6
      },
      "feelsLike": {
        "value": 13.6
      },
      "pressure": {
        "value": 1023
      },
      "cloudCover": {
        "value": 21,
        "high": 0,
        "middle": 0,
        "low": 21,
        "fog": 0
      },
      "humidity": {
        "value": 92.8
      },
      "dewPoint": {
        "value": 12.5
      },
      "start": "2025-09-06T08:00:00+02:00",
      "end": "2025-09-06T14:00:00+02:00",
      "nominalStart": "2025-09-06T06:00:00+02:00",
      "nominalEnd": "2025-09-06T12:00:00+02:00"
    },
    {
      "symbol": {
        "n": 1,
        "clouds": 0,
        "precip": 0,
        "var": "Sun",
        "sunup": false
      },
      "symbolCode": {
        "next6Hours": "clearsky_day",
        "next12Hours": "clearsky_day"
      },
      "precipitation": {
        "value": 0
      },
      "temperature": {
        "value": 22.3,
        "min": 19.6,
        "max": 23.5
      },
      "wind": {
        "direction": 59,
        "speed": 1.5
      },
      "feelsLike": {
        "value": 22.3
      },
      "pressure": {
        "value": 1021
      },
      "cloudCover": {
        "value": 2,
        "high": 0,
        "middle": 0,
        "low": 2,
        "fog": 0
      },
      "humidity": {
        "value": 68.9
      },
      "dewPoint": {
        "value": 16.5
      },
      "start": "2025-09-06T14:00:00+02:00",
      "end": "2025-09-06T20:00:00+02:00",
      "nominalStart": "2025-09-06T12:00:00+02:00",
      "nominalEnd": "2025-09-06T18:00:00+02:00"
    },
    {
      "symbol": {
        "n": 1,
        "clouds": 0,
        "precip": 0,
        "var": "Moon",
        "sunup": false
      },
      "symbolCode": {
        "next6Hours": "clearsky_night",
        "next12Hours": "fair_night"
      },
      "precipitation": {
        "value": 0
      },
      "temperature": {
        "value": 19.6,
        "min": 16.7,
        "max": 19.6
      },
      "wind": {
        "direction": 332,
        "speed": 0.5
      },
      "feelsLike": {
        "value": 19.6
      },
      "pressure": {
        "value": 1020
      },
      "cloudCover": {
        "value": 2,
        "high": 0,
        "middle": 1,
        "low": 1,
        "fog": 0
      },
      "humidity": {
        "value": 83.4
      },
      "dewPoint": {
        "value": 16.9
      },
      "start": "2025-09-06T20:00:00+02:00",
      "end": "2025-09-07T02:00:00+02:00",
      "nominalStart": "2025-09-06T18:00:00+02:00",
      "nominalEnd": "2025-09-07T00:00:00+02:00"
    },
    {
      "symbol": {
        "n": 2,
        "clouds": 1,
        "precip": 0,
        "var": "Moon",
        "sunup": false
      },
      "symbolCode": {
        "next6Hours": "fair_night",
        "next12Hours": "fair_day"
      },
      "precipitation": {
        "value": 0
      },
      "temperature": {
        "value": 16.7,
        "min": 15,
        "max": 16.7
      },
      "wind": {
        "direction": 358,
        "speed": 0.2
      },
      "feelsLike": {
        "value": 16.7
      },
      "pressure": {
        "value": 1022
      },
      "cloudCover": {
        "value": 23,
        "high": 0,
        "middle": 0,
        "low": 23,
        "fog": 0
      },
      "humidity": {
        "value": 86.4
      },
      "dewPoint": {
        "value": 14.5
      },
      "start": "2025-09-07T02:00:00+02:00",
      "end": "2025-09-07T08:00:00+02:00",
      "nominalStart": "2025-09-07T00:00:00+02:00",
      "nominalEnd": "2025-09-07T06:00:00+02:00"
    },
    {
      "symbol": {
        "n": 3,
        "clouds": 2,
        "precip": 0,
        "var": "Sun",
        "sunup": false
      },
      "symbolCode": {
        "next6Hours": "partlycloudy_day",
        "next12Hours": "fair_day"
      },
      "precipitation": {
        "value": 0
      },
      "temperature": {
        "value": 15.9,
        "min": 15.9,
        "max": 24.6
      },
      "wind": {
        "direction": 15,
        "speed": 0.1
      },
      "feelsLike": {
        "value": 15.9
      },
      "pressure": {
        "value": 1023
      },
      "cloudCover": {
        "value": 53,
        "high": 0,
        "middle": 0,
        "low": 53,
        "fog": 0
      },
      "humidity": {
        "value": 94.2
      },
      "dewPoint": {
        "value": 15.1
      },
      "start": "2025-09-07T08:00:00+02:00",
      "end": "2025-09-07T14:00:00+02:00",
      "nominalStart": "2025-09-07T06:00:00+02:00",
      "nominalEnd": "2025-09-07T12:00:00+02:00"
    },
    {
      "symbol": {
        "n": 1,
        "clouds": 0,
        "precip": 0,
        "var": "Sun",
        "sunup": false
      },
      "symbolCode": {
        "next6Hours": "clearsky_day",
        "next12Hours": "clearsky_day"
      },
      "precipitation": {
        "value": 0
      },
      "temperature": {
        "value": 24.6,
        "min": 20.8,
        "max": 25.6
      },
      "wind": {
        "direction": 55,
        "speed": 0.9
      },
      "feelsLike": {
        "value": 24.6
      },
      "pressure": {
        "value": 1022
      },
      "cloudCover": {
        "value": 0,
        "high": 0,
        "middle": 0,
        "low": 0,
        "fog": 0
      },
      "humidity": {
        "value": 66.1
      },
      "dewPoint": {
        "value": 18.1
      },
      "start": "2025-09-07T14:00:00+02:00",
      "end": "2025-09-07T20:00:00+02:00",
      "nominalStart": "2025-09-07T12:00:00+02:00",
      "nominalEnd": "2025-09-07T18:00:00+02:00"
    },
    {
      "symbol": {
        "n": 1,
        "clouds": 0,
        "precip": 0,
        "var": "Moon",
        "sunup": false
      },
      "symbolCode": {
        "next6Hours": "clearsky_night",
        "next12Hours": "clearsky_night"
      },
      "precipitation": {
        "value": 0
      },
      "temperature": {
        "value": 20.8,
        "min": 17.2,
        "max": 20.8
      },
      "wind": {
        "direction": 353,
        "speed": 0.5
      },
      "feelsLike": {
        "value": 20.8
      },
      "pressure": {
        "value": 1021
      },
      "cloudCover": {
        "value": 0,
        "high": 0,
        "middle": 0,
        "low": 0,
        "fog": 0
      },
      "humidity": {
        "value": 78.9
      },
      "dewPoint": {
        "value": 17.2
      },
      "start": "2025-09-07T20:00:00+02:00",
      "end": "2025-09-08T02:00:00+02:00",
      "nominalStart": "2025-09-07T18:00:00+02:00",
      "nominalEnd": "2025-09-08T00:00:00+02:00"
    },
    {
      "symbol": {
        "n": 1,
        "clouds": 0,
        "precip": 0,
        "var": "Moon",
        "sunup": false
      },
      "symbolCode": {
        "next6Hours": "clearsky_night",
        "next12Hours": "clearsky_day"
      },
      "precipitation": {
        "value": 0
      },
      "temperature": {
        "value": 17.2,
        "min": 15.2,
        "max": 17.2
      },
      "wind": {
        "direction": 19,
        "speed": 0.4
      },
      "feelsLike": {
        "value": 17.2
      },
      "pressure": {
        "value": 1022
      },
      "cloudCover": {
        "value": 1,
        "high": 0,
        "middle": 0,
        "low": 1,
        "fog": 0
      },
      "humidity": {
        "value": 83.6
      },
      "dewPoint": {
        "value": 14.5
      },
      "start": "2025-09-08T02:00:00+02:00",
      "end": "2025-09-08T08:00:00+02:00",
      "nominalStart": "2025-09-08T00:00:00+02:00",
      "nominalEnd": "2025-09-08T06:00:00+02:00"
    },
    {
      "symbol": {
        "n": 1,
        "clouds": 0,
        "precip": 0,
        "var": "Sun",
        "sunup": false
      },
      "symbolCode": {
        "next6Hours": "clearsky_day",
        "next12Hours": "clearsky_day"
      },
      "precipitation": {
        "value": 0
      },
      "temperature": {
        "value": 16.1,
        "min": 16.1,
        "max": 23.5
      },
      "wind": {
        "direction": 39,
        "speed": 0.6
      },
      "feelsLike": {
        "value": 16.1
      },
      "pressure": {
        "value": 1022
      },
      "cloudCover": {
        "value": 9,
        "high": 0,
        "middle": 0,
        "low": 9,
        "fog": 0
      },
      "humidity": {
        "value": 88.5
      },
      "dewPoint": {
        "value": 14.3
      },
      "start": "2025-09-08T08:00:00+02:00",
      "end": "2025-09-08T14:00:00+02:00",
      "nominalStart": "2025-09-08T06:00:00+02:00",
      "nominalEnd": "2025-09-08T12:00:00+02:00"
    },
    {
      "symbol": {
        "n": 1,
        "clouds": 0,
        "precip": 0,
        "var": "Sun",
        "sunup": false
      },
      "symbolCode": {
        "next6Hours": "clearsky_day",
        "next12Hours": "clearsky_day"
      },
      "precipitation": {
        "value": 0
      },
      "temperature": {
        "value": 23.5,
        "min": 19.9,
        "max": 23.9
      },
      "wind": {
        "direction": 41,
        "speed": 2.5
      },
      "feelsLike": {
        "value": 23.5
      },
      "pressure": {
        "value": 1020
      },
      "cloudCover": {
        "value": 0,
        "high": 0,
        "middle": 0,
        "low": 0,
        "fog": 0
      },
      "humidity": {
        "value": 61.6
      },
      "dewPoint": {
        "value": 15.9
      },
      "start": "2025-09-08T14:00:00+02:00",
      "end": "2025-09-08T20:00:00+02:00",
      "nominalStart": "2025-09-08T12:00:00+02:00",
      "nominalEnd": "2025-09-08T18:00:00+02:00"
    },
    {
      "symbol": {
        "n": 1,
        "clouds": 0,
        "precip": 0,
        "var": "Moon",
        "sunup": false
      },
      "symbolCode": {
        "next6Hours": "clearsky_night",
        "next12Hours": "clearsky_night"
      },
      "precipitation": {
        "value": 0
      },
      "temperature": {
        "value": 19.9,
        "min": 16.3,
        "max": 19.9
      },
      "wind": {
        "direction": 25,
        "speed": 2.3
      },
      "feelsLike": {
        "value": 19.9
      },
      "pressure": {
        "value": 1018
      },
      "cloudCover": {
        "value": 1,
        "high": 0,
        "middle": 0,
        "low": 1,
        "fog": 0
      },
      "humidity": {
        "value": 68.1
      },
      "dewPoint": {
        "value": 14
      },
      "start": "2025-09-08T20:00:00+02:00",
      "end": "2025-09-09T02:00:00+02:00",
      "nominalStart": "2025-09-08T18:00:00+02:00",
      "nominalEnd": "2025-09-09T00:00:00+02:00"
    },
    {
      "symbol": {
        "n": 1,
        "clouds": 0,
        "precip": 0,
        "var": "Moon",
        "sunup": false
      },
      "symbolCode": {
        "next6Hours": "clearsky_night",
        "next12Hours": "fair_day"
      },
      "precipitation": {
        "value": 0
      },
      "temperature": {
        "value": 16.3,
        "min": 14.7,
        "max": 16.3
      },
      "wind": {
        "direction": 22,
        "speed": 0.4
      },
      "feelsLike": {
        "value": 16.3
      },
      "pressure": {
        "value": 1019
      },
      "cloudCover": {
        "value": 1,
        "high": 0,
        "middle": 0,
        "low": 1,
        "fog": 0
      },
      "humidity": {
        "value": 90.1
      },
      "dewPoint": {
        "value": 14.8
      },
      "start": "2025-09-09T02:00:00+02:00",
      "end": "2025-09-09T08:00:00+02:00",
      "nominalStart": "2025-09-09T00:00:00+02:00",
      "nominalEnd": "2025-09-09T06:00:00+02:00"
    },
    {
      "symbol": {
        "n": 2,
        "clouds": 1,
        "precip": 0,
        "var": "Sun",
        "sunup": false
      },
      "symbolCode": {
        "next6Hours": "fair_day",
        "next12Hours": "fair_day"
      },
      "precipitation": {
        "value": 0
      },
      "temperature": {
        "value": 15.6,
        "min": 15.6,
        "max": 23.7
      },
      "wind": {
        "direction": 8,
        "speed": 0.5
      },
      "feelsLike": {
        "value": 15.6
      },
      "pressure": {
        "value": 1020
      },
      "cloudCover": {
        "value": 27,
        "high": 0,
        "middle": 2,
        "low": 26,
        "fog": 0
      },
      "humidity": {
        "value": 95.9
      },
      "dewPoint": {
        "value": 15.1
      },
      "start": "2025-09-09T08:00:00+02:00",
      "end": "2025-09-09T14:00:00+02:00",
      "nominalStart": "2025-09-09T06:00:00+02:00",
      "nominalEnd": "2025-09-09T12:00:00+02:00"
    },
    {
      "symbol": {
        "n": 2,
        "clouds": 1,
        "precip": 0,
        "var": "Sun",
        "sunup": false
      },
      "symbolCode": {
        "next6Hours": "fair_day",
        "next12Hours": "fair_day"
      },
      "precipitation": {
        "value": 0
      },
      "temperature": {
        "value": 23.7,
        "min": 20.9,
        "max": 24.7
      },
      "wind": {
        "direction": 52,
        "speed": 0.8
      },
      "feelsLike": {
        "value": 23.7
      },
      "pressure": {
        "value": 1019
      },
      "cloudCover": {
        "value": 28,
        "high": 20,
        "middle": 11,
        "low": 1,
        "fog": 0
      },
      "humidity": {
        "value": 65.4
      },
      "dewPoint": {
        "value": 17
      },
      "start": "2025-09-09T14:00:00+02:00",
      "end": "2025-09-09T20:00:00+02:00",
      "nominalStart": "2025-09-09T12:00:00+02:00",
      "nominalEnd": "2025-09-09T18:00:00+02:00"
    },
    {
      "symbol": {
        "n": 1,
        "clouds": 0,
        "precip": 0,
        "var": "Moon",
        "sunup": false
      },
      "symbolCode": {
        "next6Hours": "clearsky_night"
      },
      "precipitation": {
        "value": 0
      },
      "temperature": {
        "value": 20.9,
        "min": 17.7,
        "max": 20.9
      },
      "wind": {
        "direction": 17,
        "speed": 0.6
      },
      "feelsLike": {
        "value": 20.9
      },
      "pressure": {
        "value": 1018
      },
      "cloudCover": {
        "value": 12,
        "high": 0,
        "middle": 12,
        "low": 1,
        "fog": 0
      },
      "humidity": {
        "value": 75.9
      },
      "dewPoint": {
        "value": 16.7
      },
      "start": "2025-09-09T20:00:00+02:00",
      "end": "2025-09-10T02:00:00+02:00",
      "nominalStart": "2025-09-09T18:00:00+02:00",
      "nominalEnd": "2025-09-10T00:00:00+02:00"
    }
  ],
  "status": {
    "code": "Ok"
  },
  "_links": {
    "self": {
      "href": "/api/v0/locations/2-2660646/forecast"
    },
    "parent": {
      "href": "/api/v0/locations/2-2660646"
    }
  }
}
